Workbook

Sheet Cover
B2: SimPaths Codebook
B4: Date: | C4: 45974
B5: Authors: | C5: David Sonnewald, Ashley Burdett
B7: Overview: | C7: This codebook accompanies the SimPaths microsimulation model, documenting the variables used within and produced by the model. It applies to both the UK and EU variants of SimPaths.
C8: The codebook provdes definitions of each variable, specififes where each variables is created in the code and idenitifies the output file in which it can be found. Where applicable, the codebook
C9: also lists the corresponding variables from the underlying survey datasets used to construct each variable.
C11: Potenitally add a line descibing the contents of each tab?
B14: Key: | C14: ** | D14: Replace with two letter country code for European model
C25: AB: UK initial populations information to be populated.

Sheet Variables
A1: SimPaths current name | B1: Local | C1: Mod | D1: Main attribute | E1: Level | F1: Measurement | G1: Other info | H1: Statistics type | I1: Periodicity | J1: New name | K1: Description | L1: Java class | M1: Initial population | N1: Original name UK (UKHLS) | O1: Do-file UK | P1: Original name EU (EU-SILC) | Q1: Do-file EU | R1: Output file name | S1: Module | T1: Model version introduced | U1: Notes
A2: aaconsToLeisRatio | C2: {=_xlfn.IFS(S2 = Modules!$A$2,Modules!$B$2,S2 = Modules!$A$3,Modules!$B$3,S2 = Modules!$A$4,Modules!$B$4,S2 = Modules!$A$5,Modules!$B$5,S2 = Modules!$A$6,Modules!$B$6,S2 = Modules!$A$7,Modules!$B$7,S2 = Modules!$A$8,Modules!$B$8,S2 = Modules!$A$9,Modules!$B$9,S2 = Modules!$A$10,Modules!$B$10,S2 = Modules!$A$11,Modules!$B$11,S2 = Modules!$A$12,Modules!$B$12, S2 = Modules!$A$13,Modules!$B$13)} -> x | D2: ToLeisure | H2: Ratio | J2: =CONCATENATE(B2, C2,D2,E2,F2,G2,H2,I2) -> xToLeisureRatio | K2: Consumption-Leisure ratio | L2: Statistics2.java | M2: =IF(OR(O2<>"", Q2<>""),"Yes","No") -> No | R2: File: Statistics2 | S2: Consumption
A3: aadisposableIncome18to29 | C3: {=_xlfn.IFS(S3 = Modules!$A$2,Modules!$B$2,S3 = Modules!$A$3,Modules!$B$3,S3 = Modules!$A$4,Modules!$B$4,S3 = Modules!$A$5,Modules!$B$5,S3 = Modules!$A$6,Modules!$B$6,S3 = Modules!$A$7,Modules!$B$7,S3 = Modules!$A$8,Modules!$B$8,S3 = Modules!$A$9,Modules!$B$9,S3 = Modules!$A$10,Modules!$B$10,S3 = Modules!$A$11,Modules!$B$11,S3 = Modules!$A$12,Modules!$B$12, S3 = Modules!$A$13,Modules!$B$13)} -> stat | F3: Disp | G3: 18to29 | H3: Avg | J3: =CONCATENATE(B3, C3,D3,E3,F3,G3,H3,I3) -> statDisp18to29Avg | K3: Average disposable income age 18-29 | L3: Statistics2.java | M3: =IF(OR(O3<>"", Q3<>""),"Yes","No") -> No | R3: File: Statistics2 | S3: Statistical display
A4: aadisposableIncome30to54 | C4: {=_xlfn.IFS(S4 = Modules!$A$2,Modules!$B$2,S4 = Modules!$A$3,Modules!$B$3,S4 = Modules!$A$4,Modules!$B$4,S4 = Modules!$A$5,Modules!$B$5,S4 = Modules!$A$6,Modules!$B$6,S4 = Modules!$A$7,Modules!$B$7,S4 = Modules!$A$8,Modules!$B$8,S4 = Modules!$A$9,Modules!$B$9,S4 = Modules!$A$10,Modules!$B$10,S4 = Modules!$A$11,Modules!$B$11,S4 = Modules!$A$12,Modules!$B$12, S4 = Modules!$A$13,Modules!$B$13)} -> stat | F4: Disp | G4: 30to54 | H4: Avg | J4: =CONCATENATE(B4, C4,D4,E4,F4,G4,H4,I4) -> statDisp30to54Avg | K4: Average disposable income age 30-54 | L4: Statistics2.java | M4: =IF(OR(O4<>"", Q4<>""),"Yes","No") -> No | R4: File: Statistics2 | S4: Statistical display
A5: aadisposableIncome55to74 | C5: {=_xlfn.IFS(S5 = Modules!$A$2,Modules!$B$2,S5 = Modules!$A$3,Modules!$B$3,S5 = Modules!$A$4,Modules!$B$4,S5 = Modules!$A$5,Modules!$B$5,S5 = Modules!$A$6,Modules!$B$6,S5 = Modules!$A$7,Modules!$B$7,S5 = Modules!$A$8,Modules!$B$8,S5 = Modules!$A$9,Modules!$B$9,S5 = Modules!$A$10,Modules!$B$10,S5 = Modules!$A$11,Modules!$B$11,S5 = Modules!$A$12,Modules!$B$12, S5 = Modules!$A$13,Modules!$B$13)} -> stat | F5: Disp | G5: 55to74 | H5: Avg | J5: =CONCATENATE(B5, C5,D5,E5,F5,G5,H5,I5) -> statDisp55to74Avg | K5: Average disposable income age 55-74 | L5: Statistics2.java | M5: =IF(OR(O5<>"", Q5<>""),"Yes","No") -> No | R5: File: Statistics2 | S5: Statistical display
A6: aaexpenditure18to29 | C6: {=_xlfn.IFS(S6 = Modules!$A$2,Modules!$B$2,S6 = Modules!$A$3,Modules!$B$3,S6 = Modules!$A$4,Modules!$B$4,S6 = Modules!$A$5,Modules!$B$5,S6 = Modules!$A$6,Modules!$B$6,S6 = Modules!$A$7,Modules!$B$7,S6 = Modules!$A$8,Modules!$B$8,S6 = Modules!$A$9,Modules!$B$9,S6 = Modules!$A$10,Modules!$B$10,S6 = Modules!$A$11,Modules!$B$11,S6 = Modules!$A$12,Modules!$B$12, S6 = Modules!$A$13,Modules!$B$13)} -> x | G6: 18to29 | H6: Avg | J6: =CONCATENATE(B6, C6,D6,E6,F6,G6,H6,I6) -> x18to29Avg | K6: Average expenditure age 18-29 | L6: Statistics2.java | M6: =IF(OR(O6<>"", Q6<>""),"Yes","No") -> No | R6: File: Statistics2 | S6: Consumption
A7: aaexpenditure18to54 | C7: {=_xlfn.IFS(S7 = Modules!$A$2,Modules!$B$2,S7 = Modules!$A$3,Modules!$B$3,S7 = Modules!$A$4,Modules!$B$4,S7 = Modules!$A$5,Modules!$B$5,S7 = Modules!$A$6,Modules!$B$6,S7 = Modules!$A$7,Modules!$B$7,S7 = Modules!$A$8,Modules!$B$8,S7 = Modules!$A$9,Modules!$B$9,S7 = Modules!$A$10,Modules!$B$10,S7 = Modules!$A$11,Modules!$B$11,S7 = Modules!$A$12,Modules!$B$12, S7 = Modules!$A$13,Modules!$B$13)} -> x | G7: 18to54 | H7: Avg | J7: =CONCATENATE(B7, C7,D7,E7,F7,G7,H7,I7) -> x18to54Avg | K7: Average expenditure age 18-54 | L7: Statistics2.java | M7: =IF(OR(O7<>"", Q7<>""),"Yes","No") -> No | R7: File: Statistics2 | S7: Consumption
A8: aaexpenditure30to54 | C8: {=_xlfn.IFS(S8 = Modules!$A$2,Modules!$B$2,S8 = Modules!$A$3,Modules!$B$3,S8 = Modules!$A$4,Modules!$B$4,S8 = Modules!$A$5,Modules!$B$5,S8 = Modules!$A$6,Modules!$B$6,S8 = Modules!$A$7,Modules!$B$7,S8 = Modules!$A$8,Modules!$B$8,S8 = Modules!$A$9,Modules!$B$9,S8 = Modules!$A$10,Modules!$B$10,S8 = Modules!$A$11,Modules!$B$11,S8 = Modules!$A$12,Modules!$B$12, S8 = Modules!$A$13,Modules!$B$13)} -> x | G8: 30to54 | H8: Avg | J8: =CONCATENATE(B8, C8,D8,E8,F8,G8,H8,I8) -> x30to54Avg | K8: Average expenditure age 30-54 | L8: Statistics2.java | M8: =IF(OR(O8<>"", Q8<>""),"Yes","No") -> No | R8: File: Statistics2 | S8: Consumption
A9: aaexpenditure55to74 | C9: {=_xlfn.IFS(S9 = Modules!$A$2,Modules!$B$2,S9 = Modules!$A$3,Modules!$B$3,S9 = Modules!$A$4,Modules!$B$4,S9 = Modules!$A$5,Modules!$B$5,S9 = Modules!$A$6,Modules!$B$6,S9 = Modules!$A$7,Modules!$B$7,S9 = Modules!$A$8,Modules!$B$8,S9 = Modules!$A$9,Modules!$B$9,S9 = Modules!$A$10,Modules!$B$10,S9 = Modules!$A$11,Modules!$B$11,S9 = Modules!$A$12,Modules!$B$12, S9 = Modules!$A$13,Modules!$B$13)} -> x | G9: 55to74 | H9: Avg | J9: =CONCATENATE(B9, C9,D9,E9,F9,G9,H9,I9) -> x55to74Avg | K9: Average expenditure age 55-74 | L9: Statistics2.java | M9: =IF(OR(O9<>"", Q9<>""),"Yes","No") -> No | R9: File: Statistics2 | S9: Consumption
A10: aaworkNone18to29 | C10: {=_xlfn.IFS(S10 = Modules!$A$2,Modules!$B$2,S10 = Modules!$A$3,Modules!$B$3,S10 = Modules!$A$4,Modules!$B$4,S10 = Modules!$A$5,Modules!$B$5,S10 = Modules!$A$6,Modules!$B$6,S10 = Modules!$A$7,Modules!$B$7,S10 = Modules!$A$8,Modules!$B$8,S10 = Modules!$A$9,Modules!$B$9,S10 = Modules!$A$10,Modules!$B$10,S10 = Modules!$A$11,Modules!$B$11,S10 = Modules!$A$12,Modules!$B$12, S10 = Modules!$A$13,Modules!$B$13)} -> lab | D10: NoWork | G10: 18to29 | H10: Share | J10: =CONCATENATE(B10, C10,D10,E10,F10,G10,H10,I10) -> labNoWork18to29Share | K10: Share not working age 18-29 | L10: Statistics2.java | M10: =IF(OR(O10<>"", Q10<>""),"Yes","No") -> No | R10: File: Statistics2 | S10: Labour
A11: aaworkNone18to74 | C11: {=_xlfn.IFS(S11 = Modules!$A$2,Modules!$B$2,S11 = Modules!$A$3,Modules!$B$3,S11 = Modules!$A$4,Modules!$B$4,S11 = Modules!$A$5,Modules!$B$5,S11 = Modules!$A$6,Modules!$B$6,S11 = Modules!$A$7,Modules!$B$7,S11 = Modules!$A$8,Modules!$B$8,S11 = Modules!$A$9,Modules!$B$9,S11 = Modules!$A$10,Modules!$B$10,S11 = Modules!$A$11,Modules!$B$11,S11 = Modules!$A$12,Modules!$B$12, S11 = Modules!$A$13,Modules!$B$13)} -> lab | D11: NoWork | G11: 18to54 | H11: Share | J11: =CONCATENATE(B11, C11,D11,E11,F11,G11,H11,I11) -> labNoWork18to54Share | K11: Share not working age 18-74 | L11: Statistics2.java | M11: =IF(OR(O11<>"", Q11<>""),"Yes","No") -> No | R11: File: Statistics2 | S11: Labour
A12: aaworkNone30to54 | C12: {=_xlfn.IFS(S12 = Modules!$A$2,Modules!$B$2,S12 = Modules!$A$3,Modules!$B$3,S12 = Modules!$A$4,Modules!$B$4,S12 = Modules!$A$5,Modules!$B$5,S12 = Modules!$A$6,Modules!$B$6,S12 = Modules!$A$7,Modules!$B$7,S12 = Modules!$A$8,Modules!$B$8,S12 = Modules!$A$9,Modules!$B$9,S12 = Modules!$A$10,Modules!$B$10,S12 = Modules!$A$11,Modules!$B$11,S12 = Modules!$A$12,Modules!$B$12, S12 = Modules!$A$13,Modules!$B$13)} -> lab | D12: NoWork | G12: 30to54 | H12: Share | J12: =CONCATENATE(B12, C12,D12,E12,F12,G12,H12,I12) -> labNoWork30to54Share | K12: Share not working age 30-54 | L12: Statistics2.java | M12: =IF(OR(O12<>"", Q12<>""),"Yes","No") -> No | R12: File: Statistics2 | S12: Labour
A13: aaworkNone55to74 | C13: {=_xlfn.IFS(S13 = Modules!$A$2,Modules!$B$2,S13 = Modules!$A$3,Modules!$B$3,S13 = Modules!$A$4,Modules!$B$4,S13 = Modules!$A$5,Modules!$B$5,S13 = Modules!$A$6,Modules!$B$6,S13 = Modules!$A$7,Modules!$B$7,S13 = Modules!$A$8,Modules!$B$8,S13 = Modules!$A$9,Modules!$B$9,S13 = Modules!$A$10,Modules!$B$10,S13 = Modules!$A$11,Modules!$B$11,S13 = Modules!$A$12,Modules!$B$12, S13 = Modules!$A$13,Modules!$B$13)} -> lab | D13: NoWork | G13: 55to74 | H13: Share | J13: =CONCATENATE(B13, C13,D13,E13,F13,G13,H13,I13) -> labNoWork55to74Share | K13: Share not working age 55-74 | L13: Statistics2.java | M13: =IF(OR(O13<>"", Q13<>""),"Yes","No") -> No | R13: File: Statistics2 | S13: Labour
A14: adultchildflag | C14: {=_xlfn.IFS(S14 = Modules!$A$2,Modules!$B$2,S14 = Modules!$A$3,Modules!$B$3,S14 = Modules!$A$4,Modules!$B$4,S14 = Modules!$A$5,Modules!$B$5,S14 = Modules!$A$6,Modules!$B$6,S14 = Modules!$A$7,Modules!$B$7,S14 = Modules!$A$8,Modules!$B$8,S14 = Modules!$A$9,Modules!$B$9,S14 = Modules!$A$10,Modules!$B$10,S14 = Modules!$A$11,Modules!$B$11,S14 = Modules!$A$12,Modules!$B$12, S14 = Modules!$A$13,Modules!$B$13)} -> dem | D14: AdultChild | H14: Flag | J14: =CONCATENATE(B14, C14,D14,E14,F14,G14,H14,I14) -> demAdultChildFlag | K14: Adult child 0 No 1 Yes | L14: Person.java | M14: =IF(OR(O14<>"", Q14<>""),"Yes","No") -> Yes | N14: dagmother; dagfather; dag; age_become_responsible; idpartner | O14: 02_create_ukhls_variables.do | P14: idmother (rb230; urtgrp); idfather (rb220; urtgrp); dag (rb080; rx010; pb110); les_c4 (pl030; pl031; pl032; rb210; rb211) | Q14: 02_00_create_variables_**.do | S14: Demography
A15: ageGroup | C15: {=_xlfn.IFS(S15 = Modules!$A$2,Modules!$B$2,S15 = Modules!$A$3,Modules!$B$3,S15 = Modules!$A$4,Modules!$B$4,S15 = Modules!$A$5,Modules!$B$5,S15 = Modules!$A$6,Modules!$B$6,S15 = Modules!$A$7,Modules!$B$7,S15 = Modules!$A$8,Modules!$B$8,S15 = Modules!$A$9,Modules!$B$9,S15 = Modules!$A$10,Modules!$B$10,S15 = Modules!$A$11,Modules!$B$11,S15 = Modules!$A$12,Modules!$B$12, S15 = Modules!$A$13,Modules!$B$13)} -> dem | D15: AgeGroup | J15: =CONCATENATE(B15, C15,D15,E15,F15,G15,H15,I15) -> demAgeGroup | K15: Age group 1 dag >= 18 && dag < 21 2 dag >= 21 && dag < 24 3 dag >= 24 && dag < 27 4 dag >= 27 && dag < 30 5 dag >= 30 && dag < 33 6 dag >= 33 && dag < 36 7 dag >= 36 && dag < 40 8 dag >= 40 && dag < 45 9 dag >= 45 && dag < 55 10 dag >= 55 && dag < 65 11 dag >= 65 | L15: Person.java | M15: =IF(OR(O15<>"", Q15<>""),"Yes","No") -> No | S15: Demography
A16: atRiskOfPoverty | C16: {=_xlfn.IFS(S16 = Modules!$A$2,Modules!$B$2,S16 = Modules!$A$3,Modules!$B$3,S16 = Modules!$A$4,Modules!$B$4,S16 = Modules!$A$5,Modules!$B$5,S16 = Modules!$A$6,Modules!$B$6,S16 = Modules!$A$7,Modules!$B$7,S16 = Modules!$A$8,Modules!$B$8,S16 = Modules!$A$9,Modules!$B$9,S16 = Modules!$A$10,Modules!$B$10,S16 = Modules!$A$11,Modules!$B$11,S16 = Modules!$A$12,Modules!$B$12, S16 = Modules!$A$13,Modules!$B$13)} -> y | D16: Pvrty | H16: Flag | J16: =CONCATENATE(B16, C16,D16,E16,F16,G16,H16,I16) -> yPvrtyFlag | K16: At risk of poverty 0 No 1 Yes | L16: BenefitUnit.java | M16: =IF(OR(O16<>"", Q16<>""),"Yes","No") -> No | S16: Income | U16: equivalisedDisposableIncomeYearly < 60% of median household's
A17: atRiskOfPoverty_lag1 | C17: {=_xlfn.IFS(S17 = Modules!$A$2,Modules!$B$2,S17 = Modules!$A$3,Modules!$B$3,S17 = Modules!$A$4,Modules!$B$4,S17 = Modules!$A$5,Modules!$B$5,S17 = Modules!$A$6,Modules!$B$6,S17 = Modules!$A$7,Modules!$B$7,S17 = Modules!$A$8,Modules!$B$8,S17 = Modules!$A$9,Modules!$B$9,S17 = Modules!$A$10,Modules!$B$10,S17 = Modules!$A$11,Modules!$B$11,S17 = Modules!$A$12,Modules!$B$12, S17 = Modules!$A$13,Modules!$B$13)} -> y | D17: Pvrty | H17: Flag | I17: L1 | J17: =CONCATENATE(B17, C17,D17,E17,F17,G17,H17,I17) -> yPvrtyFlagL1 | K17: Lag(1) of atRiskOfPoverty | L17: BenefitUnit.java | M17: =IF(OR(O17<>"", Q17<>""),"Yes","No") -> No | S17: Income
A18: avkids18to29 | C18: {=_xlfn.IFS(S18 = Modules!$A$2,Modules!$B$2,S18 = Modules!$A$3,Modules!$B$3,S18 = Modules!$A$4,Modules!$B$4,S18 = Modules!$A$5,Modules!$B$5,S18 = Modules!$A$6,Modules!$B$6,S18 = Modules!$A$7,Modules!$B$7,S18 = Modules!$A$8,Modules!$B$8,S18 = Modules!$A$9,Modules!$B$9,S18 = Modules!$A$10,Modules!$B$10,S18 = Modules!$A$11,Modules!$B$11,S18 = Modules!$A$12,Modules!$B$12, S18 = Modules!$A$13,Modules!$B$13)} -> dem | D18: NChild | G18: 18to29 | H18: Avg | J18: =CONCATENATE(B18, C18,D18,E18,F18,G18,H18,I18) -> demNChild18to29Avg | K18: Average number of children age 18-29 | L18: Statistics2.java | M18: =IF(OR(O18<>"", Q18<>""),"Yes","No") -> No | R18: File: Statistics2 | S18: Demography
A19: avkids30to54 | C19: {=_xlfn.IFS(S19 = Modules!$A$2,Modules!$B$2,S19 = Modules!$A$3,Modules!$B$3,S19 = Modules!$A$4,Modules!$B$4,S19 = Modules!$A$5,Modules!$B$5,S19 = Modules!$A$6,Modules!$B$6,S19 = Modules!$A$7,Modules!$B$7,S19 = Modules!$A$8,Modules!$B$8,S19 = Modules!$A$9,Modules!$B$9,S19 = Modules!$A$10,Modules!$B$10,S19 = Modules!$A$11,Modules!$B$11,S19 = Modules!$A$12,Modules!$B$12, S19 = Modules!$A$13,Modules!$B$13)} -> dem | D19: NChild | G19: 30to54 | H19: Avg | J19: =CONCATENATE(B19, C19,D19,E19,F19,G19,H19,I19) -> demNChild30to54Avg | K19: Average number of children age 30-54 | L19: Statistics2.java | M19: =IF(OR(O19<>"", Q19<>""),"Yes","No") -> No | R19: File: Statistics2 | S19: Demography
A20: avkids55to74 | C20: {=_xlfn.IFS(S20 = Modules!$A$2,Modules!$B$2,S20 = Modules!$A$3,Modules!$B$3,S20 = Modules!$A$4,Modules!$B$4,S20 = Modules!$A$5,Modules!$B$5,S20 = Modules!$A$6,Modules!$B$6,S20 = Modules!$A$7,Modules!$B$7,S20 = Modules!$A$8,Modules!$B$8,S20 = Modules!$A$9,Modules!$B$9,S20 = Modules!$A$10,Modules!$B$10,S20 = Modules!$A$11,Modules!$B$11,S20 = Modules!$A$12,Modules!$B$12, S20 = Modules!$A$13,Modules!$B$13)} -> dem | D20: NChild | G20: 55to74 | H20: Avg | J20: =CONCATENATE(B20, C20,D20,E20,F20,G20,H20,I20) -> demNChild55to74Avg | K20: Average number of children age 55-74 | L20: Statistics2.java | M20: =IF(OR(O20<>"", Q20<>""),"Yes","No") -> No | R20: File: Statistics2 | S20: Demography
A21: aworkFulltime18to29 | C21: {=_xlfn.IFS(S21 = Modules!$A$2,Modules!$B$2,S21 = Modules!$A$3,Modules!$B$3,S21 = Modules!$A$4,Modules!$B$4,S21 = Modules!$A$5,Modules!$B$5,S21 = Modules!$A$6,Modules!$B$6,S21 = Modules!$A$7,Modules!$B$7,S21 = Modules!$A$8,Modules!$B$8,S21 = Modules!$A$9,Modules!$B$9,S21 = Modules!$A$10,Modules!$B$10,S21 = Modules!$A$11,Modules!$B$11,S21 = Modules!$A$12,Modules!$B$12, S21 = Modules!$A$13,Modules!$B$13)} -> lab | D21: WorkFullTime | G21: 18to29 | H21: Share | J21: =CONCATENATE(B21, C21,D21,E21,F21,G21,H21,I21) -> labWorkFullTime18to29Share | K21: Share working full time age 18-29 | L21: Statistics2.java | M21: =IF(OR(O21<>"", Q21<>""),"Yes","No") -> No | R21: File: Statistics2 | S21: Labour
A22: aworkFulltime30to54 | C22: {=_xlfn.IFS(S22 = Modules!$A$2,Modules!$B$2,S22 = Modules!$A$3,Modules!$B$3,S22 = Modules!$A$4,Modules!$B$4,S22 = Modules!$A$5,Modules!$B$5,S22 = Modules!$A$6,Modules!$B$6,S22 = Modules!$A$7,Modules!$B$7,S22 = Modules!$A$8,Modules!$B$8,S22 = Modules!$A$9,Modules!$B$9,S22 = Modules!$A$10,Modules!$B$10,S22 = Modules!$A$11,Modules!$B$11,S22 = Modules!$A$12,Modules!$B$12, S22 = Modules!$A$13,Modules!$B$13)} -> lab | D22: WorkFullTime | G22: 30to54 | H22: Share | J22: =CONCATENATE(B22, C22,D22,E22,F22,G22,H22,I22) -> labWorkFullTime30to54Share | K22: Share working full time age 30-54 | L22: Statistics2.java | M22: =IF(OR(O22<>"", Q22<>""),"Yes","No") -> No | R22: File: Statistics2 | S22: Labour
A23: aworkFulltime55to74 | C23: {=_xlfn.IFS(S23 = Modules!$A$2,Modules!$B$2,S23 = Modules!$A$3,Modules!$B$3,S23 = Modules!$A$4,Modules!$B$4,S23 = Modules!$A$5,Modules!$B$5,S23 = Modules!$A$6,Modules!$B$6,S23 = Modules!$A$7,Modules!$B$7,S23 = Modules!$A$8,Modules!$B$8,S23 = Modules!$A$9,Modules!$B$9,S23 = Modules!$A$10,Modules!$B$10,S23 = Modules!$A$11,Modules!$B$11,S23 = Modules!$A$12,Modules!$B$12, S23 = Modules!$A$13,Modules!$B$13)} -> lab | D23: WorkFullTime | G23: 55to74 | H23: Share | J23: =CONCATENATE(B23, C23,D23,E23,F23,G23,H23,I23) -> labWorkFullTime55to74Share | K23: Share working full time age 55-74 | L23: Statistics2.java | M23: =IF(OR(O23<>"", Q23<>""),"Yes","No") -> No | R23: File: Statistics2 | S23: Labour
A24: aworkParttime18to29 | C24: {=_xlfn.IFS(S24 = Modules!$A$2,Modules!$B$2,S24 = Modules!$A$3,Modules!$B$3,S24 = Modules!$A$4,Modules!$B$4,S24 = Modules!$A$5,Modules!$B$5,S24 = Modules!$A$6,Modules!$B$6,S24 = Modules!$A$7,Modules!$B$7,S24 = Modules!$A$8,Modules!$B$8,S24 = Modules!$A$9,Modules!$B$9,S24 = Modules!$A$10,Modules!$B$10,S24 = Modules!$A$11,Modules!$B$11,S24 = Modules!$A$12,Modules!$B$12, S24 = Modules!$A$13,Modules!$B$13)} -> lab | D24: WorkPartTime | G24: 18to29 | H24: Share | J24: =CONCATENATE(B24, C24,D24,E24,F24,G24,H24,I24) -> labWorkPartTime18to29Share | K24: Share working part time age 18-29 | L24: Statistics2.java | M24: =IF(OR(O24<>"", Q24<>""),"Yes","No") -> No | R24: File: Statistics2 | S24: Labour
A25: aworkParttime30to54 | C25: {=_xlfn.IFS(S25 = Modules!$A$2,Modules!$B$2,S25 = Modules!$A$3,Modules!$B$3,S25 = Modules!$A$4,Modules!$B$4,S25 = Modules!$A$5,Modules!$B$5,S25 = Modules!$A$6,Modules!$B$6,S25 = Modules!$A$7,Modules!$B$7,S25 = Modules!$A$8,Modules!$B$8,S25 = Modules!$A$9,Modules!$B$9,S25 = Modules!$A$10,Modules!$B$10,S25 = Modules!$A$11,Modules!$B$11,S25 = Modules!$A$12,Modules!$B$12, S25 = Modules!$A$13,Modules!$B$13)} -> lab | D25: WorkPartTime | G25: 30to54 | H25: Share | J25: =CONCATENATE(B25, C25,D25,E25,F25,G25,H25,I25) -> labWorkPartTime30to54Share | K25: Share working part time age 30-54 | L25: Statistics2.java | M25: =IF(OR(O25<>"", Q25<>""),"Yes","No") -> No | R25: File: Statistics2 | S25: Labour
A26: aworkParttime55to74 | C26: {=_xlfn.IFS(S26 = Modules!$A$2,Modules!$B$2,S26 = Modules!$A$3,Modules!$B$3,S26 = Modules!$A$4,Modules!$B$4,S26 = Modules!$A$5,Modules!$B$5,S26 = Modules!$A$6,Modules!$B$6,S26 = Modules!$A$7,Modules!$B$7,S26 = Modules!$A$8,Modules!$B$8,S26 = Modules!$A$9,Modules!$B$9,S26 = Modules!$A$10,Modules!$B$10,S26 = Modules!$A$11,Modules!$B$11,S26 = Modules!$A$12,Modules!$B$12, S26 = Modules!$A$13,Modules!$B$13)} -> lab | D26: WorkPartTime | G26: 55to74 | H26: Share | J26: =CONCATENATE(B26, C26,D26,E26,F26,G26,H26,I26) -> labWorkPartTime55to74Share | K26: Share working part time age 55-74 | L26: Statistics2.java | M26: =IF(OR(O26<>"", Q26<>""),"Yes","No") -> No | R26: File: Statistics2 | S26: Labour
A27: benefitsReceivedPerMonth | C27: {=_xlfn.IFS(S27 = Modules!$A$2,Modules!$B$2,S27 = Modules!$A$3,Modules!$B$3,S27 = Modules!$A$4,Modules!$B$4,S27 = Modules!$A$5,Modules!$B$5,S27 = Modules!$A$6,Modules!$B$6,S27 = Modules!$A$7,Modules!$B$7,S27 = Modules!$A$8,Modules!$B$8,S27 = Modules!$A$9,Modules!$B$9,S27 = Modules!$A$10,Modules!$B$10,S27 = Modules!$A$11,Modules!$B$11,S27 = Modules!$A$12,Modules!$B$12, S27 = Modules!$A$13,Modules!$B$13)} -> y | D27: Ben | F27: Amount | I27: Month | J27: =CONCATENATE(B27, C27,D27,E27,F27,G27,H27,I27) -> yBenAmountMonth | K27: Amount of benefits received per month | L27: BenefitUnit.java | M27: =IF(OR(O27<>"", Q27<>""),"Yes","No") -> No | S27: Income
A28: bornInSimulation | C28: {=_xlfn.IFS(S28 = Modules!$A$2,Modules!$B$2,S28 = Modules!$A$3,Modules!$B$3,S28 = Modules!$A$4,Modules!$B$4,S28 = Modules!$A$5,Modules!$B$5,S28 = Modules!$A$6,Modules!$B$6,S28 = Modules!$A$7,Modules!$B$7,S28 = Modules!$A$8,Modules!$B$8,S28 = Modules!$A$9,Modules!$B$9,S28 = Modules!$A$10,Modules!$B$10,S28 = Modules!$A$11,Modules!$B$11,S28 = Modules!$A$12,Modules!$B$12, S28 = Modules!$A$13,Modules!$B$13)} -> dem | D28: BornInSim | H28: Flag | J28: =CONCATENATE(B28, C28,D28,E28,F28,G28,H28,I28) -> demBornInSimFlag | K28: Flag to keep track of newborns TRUE FALSE | L28: Person.java | M28: =IF(OR(O28<>"", Q28<>""),"Yes","No") -> No | S28: Demography
A29: careFormalExpenditureWeekly | C29: {=_xlfn.IFS(S29 = Modules!$A$2,Modules!$B$2,S29 = Modules!$A$3,Modules!$B$3,S29 = Modules!$A$4,Modules!$B$4,S29 = Modules!$A$5,Modules!$B$5,S29 = Modules!$A$6,Modules!$B$6,S29 = Modules!$A$7,Modules!$B$7,S29 = Modules!$A$8,Modules!$B$8,S29 = Modules!$A$9,Modules!$B$9,S29 = Modules!$A$10,Modules!$B$10,S29 = Modules!$A$11,Modules!$B$11,S29 = Modules!$A$12,Modules!$B$12, S29 = Modules!$A$13,Modules!$B$13)} -> x | D29: Care | G29: Formal | I29: Week | J29: =CONCATENATE(B29, C29,D29,E29,F29,G29,H29,I29) -> xCareFormalWeek | K29: Cost for weekly formal social care received | L29: Person.java | M29: =IF(OR(O29<>"", Q29<>""),"Yes","No") -> No | S29: Consumption
A30: careHoursFromDaughterWeekly | C30: {=_xlfn.IFS(S30 = Modules!$A$2,Modules!$B$2,S30 = Modules!$A$3,Modules!$B$3,S30 = Modules!$A$4,Modules!$B$4,S30 = Modules!$A$5,Modules!$B$5,S30 = Modules!$A$6,Modules!$B$6,S30 = Modules!$A$7,Modules!$B$7,S30 = Modules!$A$8,Modules!$B$8,S30 = Modules!$A$9,Modules!$B$9,S30 = Modules!$A$10,Modules!$B$10,S30 = Modules!$A$11,Modules!$B$11,S30 = Modules!$A$12,Modules!$B$12, S30 = Modules!$A$13,Modules!$B$13)} -> care | D30: Hrs | G30: FromDaughter | I30: Week | J30: =CONCATENATE(B30, C30,D30,E30,F30,G30,H30,I30) -> careHrsFromDaughterWeek | K30: Weekly hours of social care received from the daughter | L30: Person.java | M30: =IF(OR(O30<>"", Q30<>""),"Yes","No") -> No | S30: Social care
A31: careHoursFromDaughterWeekly_lag1 | C31: {=_xlfn.IFS(S31 = Modules!$A$2,Modules!$B$2,S31 = Modules!$A$3,Modules!$B$3,S31 = Modules!$A$4,Modules!$B$4,S31 = Modules!$A$5,Modules!$B$5,S31 = Modules!$A$6,Modules!$B$6,S31 = Modules!$A$7,Modules!$B$7,S31 = Modules!$A$8,Modules!$B$8,S31 = Modules!$A$9,Modules!$B$9,S31 = Modules!$A$10,Modules!$B$10,S31 = Modules!$A$11,Modules!$B$11,S31 = Modules!$A$12,Modules!$B$12, S31 = Modules!$A$13,Modules!$B$13)} -> care | D31: Hrs | G31: FromDaughter | I31: WeekL1 | J31: =CONCATENATE(B31, C31,D31,E31,F31,G31,H31,I31) -> careHrsFromDaughterWeekL1 | K31: Lag(1) of careHoursFromDaughterWeekly | L31: Person.java | M31: =IF(OR(O31<>"", Q31<>""),"Yes","No") -> No | S31: Social care
A32: careHoursFromFormalWeekly | C32: {=_xlfn.IFS(S32 = Modules!$A$2,Modules!$B$2,S32 = Modules!$A$3,Modules!$B$3,S32 = Modules!$A$4,Modules!$B$4,S32 = Modules!$A$5,Modules!$B$5,S32 = Modules!$A$6,Modules!$B$6,S32 = Modules!$A$7,Modules!$B$7,S32 = Modules!$A$8,Modules!$B$8,S32 = Modules!$A$9,Modules!$B$9,S32 = Modules!$A$10,Modules!$B$10,S32 = Modules!$A$11,Modules!$B$11,S32 = Modules!$A$12,Modules!$B$12, S32 = Modules!$A$13,Modules!$B$13)} -> care | D32: Hrs | G32: Formal | I32: Week | J32: =CONCATENATE(B32, C32,D32,E32,F32,G32,H32,I32) -> careHrsFormalWeek | K32: Weekly hours of formal social care received | L32: Person.java | M32: =IF(OR(O32<>"", Q32<>""),"Yes","No") -> No | S32: Social care
A33: careHoursFromFormalWeekly_lag1 | C33: {=_xlfn.IFS(S33 = Modules!$A$2,Modules!$B$2,S33 = Modules!$A$3,Modules!$B$3,S33 = Modules!$A$4,Modules!$B$4,S33 = Modules!$A$5,Modules!$B$5,S33 = Modules!$A$6,Modules!$B$6,S33 = Modules!$A$7,Modules!$B$7,S33 = Modules!$A$8,Modules!$B$8,S33 = Modules!$A$9,Modules!$B$9,S33 = Modules!$A$10,Modules!$B$10,S33 = Modules!$A$11,Modules!$B$11,S33 = Modules!$A$12,Modules!$B$12, S33 = Modules!$A$13,Modules!$B$13)} -> care | D33: Hrs | G33: Formal | I33: WeekL1 | J33: =CONCATENATE(B33, C33,D33,E33,F33,G33,H33,I33) -> careHrsFormalWeekL1 | K33: Lag(1) of careHoursFromFormalWeekly | L33: Person.java | M33: =IF(OR(O33<>"", Q33<>""),"Yes","No") -> No | S33: Social care
A34: careHoursFromOtherWeekly | C34: {=_xlfn.IFS(S34 = Modules!$A$2,Modules!$B$2,S34 = Modules!$A$3,Modules!$B$3,S34 = Modules!$A$4,Modules!$B$4,S34 = Modules!$A$5,Modules!$B$5,S34 = Modules!$A$6,Modules!$B$6,S34 = Modules!$A$7,Modules!$B$7,S34 = Modules!$A$8,Modules!$B$8,S34 = Modules!$A$9,Modules!$B$9,S34 = Modules!$A$10,Modules!$B$10,S34 = Modules!$A$11,Modules!$B$11,S34 = Modules!$A$12,Modules!$B$12, S34 = Modules!$A$13,Modules!$B$13)} -> care | D34: Hrs | G34: FromOther | I34: Week | J34: =CONCATENATE(B34, C34,D34,E34,F34,G34,H34,I34) -> careHrsFromOtherWeek | K34: Weekly hours of social care received from others | L34: Person.java | M34: =IF(OR(O34<>"", Q34<>""),"Yes","No") -> No | S34: Social care
A35: careHoursFromOtherWeekly_lag1 | C35: {=_xlfn.IFS(S35 = Modules!$A$2,Modules!$B$2,S35 = Modules!$A$3,Modules!$B$3,S35 = Modules!$A$4,Modules!$B$4,S35 = Modules!$A$5,Modules!$B$5,S35 = Modules!$A$6,Modules!$B$6,S35 = Modules!$A$7,Modules!$B$7,S35 = Modules!$A$8,Modules!$B$8,S35 = Modules!$A$9,Modules!$B$9,S35 = Modules!$A$10,Modules!$B$10,S35 = Modules!$A$11,Modules!$B$11,S35 = Modules!$A$12,Modules!$B$12, S35 = Modules!$A$13,Modules!$B$13)} -> care | D35: Hrs | G35: FromOther | I35: WeekL1 | J35: =CONCATENATE(B35, C35,D35,E35,F35,G35,H35,I35) -> careHrsFromOtherWeekL1 | K35: Lag(1) of careHoursFromOtherWeekly | L35: Person.java | M35: =IF(OR(O35<>"", Q35<>""),"Yes","No") -> No | S35: Social care
A36: careHoursFromParentWeekly | C36: {=_xlfn.IFS(S36 = Modules!$A$2,Modules!$B$2,S36 = Modules!$A$3,Modules!$B$3,S36 = Modules!$A$4,Modules!$B$4,S36 = Modules!$A$5,Modules!$B$5,S36 = Modules!$A$6,Modules!$B$6,S36 = Modules!$A$7,Modules!$B$7,S36 = Modules!$A$8,Modules!$B$8,S36 = Modules!$A$9,Modules!$B$9,S36 = Modules!$A$10,Modules!$B$10,S36 = Modules!$A$11,Modules!$B$11,S36 = Modules!$A$12,Modules!$B$12, S36 = Modules!$A$13,Modules!$B$13)} -> care | D36: Hrs | G36: FromParent | I36: Week | J36: =CONCATENATE(B36, C36,D36,E36,F36,G36,H36,I36) -> careHrsFromParentWeek | K36: Weekly hours of social care received from the parents | L36: Person.java | M36: =IF(OR(O36<>"", Q36<>""),"Yes","No") -> No | S36: Social care
A37: careHoursFromParentWeekly_lag1 | C37: {=_xlfn.IFS(S37 = Modules!$A$2,Modules!$B$2,S37 = Modules!$A$3,Modules!$B$3,S37 = Modules!$A$4,Modules!$B$4,S37 = Modules!$A$5,Modules!$B$5,S37 = Modules!$A$6,Modules!$B$6,S37 = Modules!$A$7,Modules!$B$7,S37 = Modules!$A$8,Modules!$B$8,S37 = Modules!$A$9,Modules!$B$9,S37 = Modules!$A$10,Modules!$B$10,S37 = Modules!$A$11,Modules!$B$11,S37 = Modules!$A$12,Modules!$B$12, S37 = Modules!$A$13,Modules!$B$13)} -> care | D37: Hrs | G37: FromParent | I37: WeekL1 | J37: =CONCATENATE(B37, C37,D37,E37,F37,G37,H37,I37) -> careHrsFromParentWeekL1 | K37: Lag(1) of careHoursFromParentWeekly | L37: Person.java | M37: =IF(OR(O37<>"", Q37<>""),"Yes","No") -> No | S37: Social care
A38: careHoursFromPartnerWeekly | C38: {=_xlfn.IFS(S38 = Modules!$A$2,Modules!$B$2,S38 = Modules!$A$3,Modules!$B$3,S38 = Modules!$A$4,Modules!$B$4,S38 = Modules!$A$5,Modules!$B$5,S38 = Modules!$A$6,Modules!$B$6,S38 = Modules!$A$7,Modules!$B$7,S38 = Modules!$A$8,Modules!$B$8,S38 = Modules!$A$9,Modules!$B$9,S38 = Modules!$A$10,Modules!$B$10,S38 = Modules!$A$11,Modules!$B$11,S38 = Modules!$A$12,Modules!$B$12, S38 = Modules!$A$13,Modules!$B$13)} -> care | D38: Hrs | G38: FromPartner | I38: Week | J38: =CONCATENATE(B38, C38,D38,E38,F38,G38,H38,I38) -> careHrsFromPartnerWeek | K38: Weekly hours of social care received from the partner | L38: Person.java | M38: =IF(OR(O38<>"", Q38<>""),"Yes","No") -> No | S38: Social care
A39: careHoursFromPartnerWeekly_lag1 | C39: {=_xlfn.IFS(S39 = Modules!$A$2,Modules!$B$2,S39 = Modules!$A$3,Modules!$B$3,S39 = Modules!$A$4,Modules!$B$4,S39 = Modules!$A$5,Modules!$B$5,S39 = Modules!$A$6,Modules!$B$6,S39 = Modules!$A$7,Modules!$B$7,S39 = Modules!$A$8,Modules!$B$8,S39 = Modules!$A$9,Modules!$B$9,S39 = Modules!$A$10,Modules!$B$10,S39 = Modules!$A$11,Modules!$B$11,S39 = Modules!$A$12,Modules!$B$12, S39 = Modules!$A$13,Modules!$B$13)} -> care | D39: Hrs | G39: FromPartner | I39: WeekL1 | J39: =CONCATENATE(B39, C39,D39,E39,F39,G39,H39,I39) -> careHrsFromPartnerWeekL1 | K39: Lag(1) of careHoursFromPartnerWeekly | L39: Person.java | M39: =IF(OR(O39<>"", Q39<>""),"Yes","No") -> No | S39: Social care
A40: careHoursFromSonWeekly | C40: {=_xlfn.IFS(S40 = Modules!$A$2,Modules!$B$2,S40 = Modules!$A$3,Modules!$B$3,S40 = Modules!$A$4,Modules!$B$4,S40 = Modules!$A$5,Modules!$B$5,S40 = Modules!$A$6,Modules!$B$6,S40 = Modules!$A$7,Modules!$B$7,S40 = Modules!$A$8,Modules!$B$8,S40 = Modules!$A$9,Modules!$B$9,S40 = Modules!$A$10,Modules!$B$10,S40 = Modules!$A$11,Modules!$B$11,S40 = Modules!$A$12,Modules!$B$12, S40 = Modules!$A$13,Modules!$B$13)} -> care | D40: Hrs | G40: FromSon | I40: Week | J40: =CONCATENATE(B40, C40,D40,E40,F40,G40,H40,I40) -> careHrsFromSonWeek | K40: Weekly hours of social care received from the son | L40: Person.java | M40: =IF(OR(O40<>"", Q40<>""),"Yes","No") -> No | S40: Social care
A41: careHoursFromSonWeekly_lag1 | C41: {=_xlfn.IFS(S41 = Modules!$A$2,Modules!$B$2,S41 = Modules!$A$3,Modules!$B$3,S41 = Modules!$A$4,Modules!$B$4,S41 = Modules!$A$5,Modules!$B$5,S41 = Modules!$A$6,Modules!$B$6,S41 = Modules!$A$7,Modules!$B$7,S41 = Modules!$A$8,Modules!$B$8,S41 = Modules!$A$9,Modules!$B$9,S41 = Modules!$A$10,Modules!$B$10,S41 = Modules!$A$11,Modules!$B$11,S41 = Modules!$A$12,Modules!$B$12, S41 = Modules!$A$13,Modules!$B$13)} -> care | D41: Hrs | G41: FromSon | I41: WeekL1 | J41: =CONCATENATE(B41, C41,D41,E41,F41,G41,H41,I41) -> careHrsFromSonWeekL1 | K41: Lag(1) of careHoursFromSonWeekly | L41: Person.java | M41: =IF(OR(O41<>"", Q41<>""),"Yes","No") -> No | S41: Social care
A42: carehoursprovidedweekly | C42: {=_xlfn.IFS(S42 = Modules!$A$2,Modules!$B$2,S42 = Modules!$A$3,Modules!$B$3,S42 = Modules!$A$4,Modules!$B$4,S42 = Modules!$A$5,Modules!$B$5,S42 = Modules!$A$6,Modules!$B$6,S42 = Modules!$A$7,Modules!$B$7,S42 = Modules!$A$8,Modules!$B$8,S42 = Modules!$A$9,Modules!$B$9,S42 = Modules!$A$10,Modules!$B$10,S42 = Modules!$A$11,Modules!$B$11,S42 = Modules!$A$12,Modules!$B$12, S42 = Modules!$A$13,Modules!$B$13)} -> care | D42: Hrs | G42: Provided | I42: Week | J42: =CONCATENATE(B42, C42,D42,E42,F42,G42,H42,I42) -> careHrsProvidedWeek | K42: Weekly hours of care provided (capped) | L42: Person.java | M42: =IF(OR(O42<>"", Q42<>""),"Yes","No") -> Yes | N42: aidhrs | O42: 04_social_care_provided | S42: Social care | U42: (<= 168)
A43: careHoursProvidedWeekly | C43: {=_xlfn.IFS(S43 = Modules!$A$2,Modules!$B$2,S43 = Modules!$A$3,Modules!$B$3,S43 = Modules!$A$4,Modules!$B$4,S43 = Modules!$A$5,Modules!$B$5,S43 = Modules!$A$6,Modules!$B$6,S43 = Modules!$A$7,Modules!$B$7,S43 = Modules!$A$8,Modules!$B$8,S43 = Modules!$A$9,Modules!$B$9,S43 = Modules!$A$10,Modules!$B$10,S43 = Modules!$A$11,Modules!$B$11,S43 = Modules!$A$12,Modules!$B$12, S43 = Modules!$A$13,Modules!$B$13)} -> care | D43: Hrs | G43: Provided | I43: Week | J43: =CONCATENATE(B43, C43,D43,E43,F43,G43,H43,I43) -> careHrsProvidedWeek | K43: Weekly hours of care provided | L43: Person.java | M43: =IF(OR(O43<>"", Q43<>""),"Yes","No") -> No | S43: Social care | U43: See Initial Populations: carehoursprovidedweekly
A44: carewho | C44: {=_xlfn.IFS(S44 = Modules!$A$2,Modules!$B$2,S44 = Modules!$A$3,Modules!$B$3,S44 = Modules!$A$4,Modules!$B$4,S44 = Modules!$A$5,Modules!$B$5,S44 = Modules!$A$6,Modules!$B$6,S44 = Modules!$A$7,Modules!$B$7,S44 = Modules!$A$8,Modules!$B$8,S44 = Modules!$A$9,Modules!$B$9,S44 = Modules!$A$10,Modules!$B$10,S44 = Modules!$A$11,Modules!$B$11,S44 = Modules!$A$12,Modules!$B$12, S44 = Modules!$A$13,Modules!$B$13)} -> care | G44: Who | J44: =CONCATENATE(B44, C44,D44,E44,F44,G44,H44,I44) -> careWho | K44: Who provides care to the person 1 Partner only 2 Partner and non-partner 3 Non-partner only | L44: Initial Populations | M44: =IF(OR(O44<>"", Q44<>""),"Yes","No") -> Yes | N44: care_partner; care_nonpartner | O44: 04_social_care_provided | S44: Social care
A45: childcareCostPerWeek | C45: {=_xlfn.IFS(S45 = Modules!$A$2,Modules!$B$2,S45 = Modules!$A$3,Modules!$B$3,S45 = Modules!$A$4,Modules!$B$4,S45 = Modules!$A$5,Modules!$B$5,S45 = Modules!$A$6,Modules!$B$6,S45 = Modules!$A$7,Modules!$B$7,S45 = Modules!$A$8,Modules!$B$8,S45 = Modules!$A$9,Modules!$B$9,S45 = Modules!$A$10,Modules!$B$10,S45 = Modules!$A$11,Modules!$B$11,S45 = Modules!$A$12,Modules!$B$12, S45 = Modules!$A$13,Modules!$B$13)} -> x | D45: ChildCare | I45: Week | J45: =CONCATENATE(B45, C45,D45,E45,F45,G45,H45,I45) -> xChildCareWeek | K45: Amount spent for weekly childcare | L45: BenefitUnit.java | M45: =IF(OR(O45<>"", Q45<>""),"Yes","No") -> No | S45: Consumption
A46: clonedFlag | C46: {=_xlfn.IFS(S46 = Modules!$A$2,Modules!$B$2,S46 = Modules!$A$3,Modules!$B$3,S46 = Modules!$A$4,Modules!$B$4,S46 = Modules!$A$5,Modules!$B$5,S46 = Modules!$A$6,Modules!$B$6,S46 = Modules!$A$7,Modules!$B$7,S46 = Modules!$A$8,Modules!$B$8,S46 = Modules!$A$9,Modules!$B$9,S46 = Modules!$A$10,Modules!$B$10,S46 = Modules!$A$11,Modules!$B$11,S46 = Modules!$A$12,Modules!$B$12, S46 = Modules!$A$13,Modules!$B$13)} -> dem | D46: Cloned | H46: Flag | J46: =CONCATENATE(B46, C46,D46,E46,F46,G46,H46,I46) -> demClonedFlag | K46: Person object originates as clone of another Person object | L46: Person.java | M46: =IF(OR(O46<>"", Q46<>""),"Yes","No") -> No | S46: Demography
A47: covidModuleGrossLabourIncome_Baseline | C47: {=_xlfn.IFS(S47 = Modules!$A$2,Modules!$B$2,S47 = Modules!$A$3,Modules!$B$3,S47 = Modules!$A$4,Modules!$B$4,S47 = Modules!$A$5,Modules!$B$5,S47 = Modules!$A$6,Modules!$B$6,S47 = Modules!$A$7,Modules!$B$7,S47 = Modules!$A$8,Modules!$B$8,S47 = Modules!$A$9,Modules!$B$9,S47 = Modules!$A$10,Modules!$B$10,S47 = Modules!$A$11,Modules!$B$11,S47 = Modules!$A$12,Modules!$B$12, S47 = Modules!$A$13,Modules!$B$13)} -> covid | D47: YLab | F47: Gross | J47: =CONCATENATE(B47, C47,D47,E47,F47,G47,H47,I47) -> covidYLabGross | K47: Gross labour income in the Covid Module | L47: Person.java | M47: =IF(OR(O47<>"", Q47<>""),"Yes","No") -> No | S47: Covid
A48: covidModuleGrossLabourIncome_lag1 | C48: {=_xlfn.IFS(S48 = Modules!$A$2,Modules!$B$2,S48 = Modules!$A$3,Modules!$B$3,S48 = Modules!$A$4,Modules!$B$4,S48 = Modules!$A$5,Modules!$B$5,S48 = Modules!$A$6,Modules!$B$6,S48 = Modules!$A$7,Modules!$B$7,S48 = Modules!$A$8,Modules!$B$8,S48 = Modules!$A$9,Modules!$B$9,S48 = Modules!$A$10,Modules!$B$10,S48 = Modules!$A$11,Modules!$B$11,S48 = Modules!$A$12,Modules!$B$12, S48 = Modules!$A$13,Modules!$B$13)} -> covid | D48: YLab | F48: Gross | I48: L1 | J48: =CONCATENATE(B48, C48,D48,E48,F48,G48,H48,I48) -> covidYLabGrossL1 | K48: Lag (1) of covidModuleGrossLabourIncome | L48: Person.java | M48: =IF(OR(O48<>"", Q48<>""),"Yes","No") -> No | S48: Covid
A49: covidModuleGrossLabourIncomeBaseline_Xt5 | C49: {=_xlfn.IFS(S49 = Modules!$A$2,Modules!$B$2,S49 = Modules!$A$3,Modules!$B$3,S49 = Modules!$A$4,Modules!$B$4,S49 = Modules!$A$5,Modules!$B$5,S49 = Modules!$A$6,Modules!$B$6,S49 = Modules!$A$7,Modules!$B$7,S49 = Modules!$A$8,Modules!$B$8,S49 = Modules!$A$9,Modules!$B$9,S49 = Modules!$A$10,Modules!$B$10,S49 = Modules!$A$11,Modules!$B$11,S49 = Modules!$A$12,Modules!$B$12, S49 = Modules!$A$13,Modules!$B$13)} -> covid | D49: YLab | F49: Gross | G49: Xt5 | J49: =CONCATENATE(B49, C49,D49,E49,F49,G49,H49,I49) -> covidYLabGrossXt5 | K49: Gross labour quintile in simulation baseline | L49: Person.java | M49: =IF(OR(O49<>"", Q49<>""),"Yes","No") -> No | S49: Covid | U49: Quintiles
A50: covidModuleReceivesSEISS | C50: {=_xlfn.IFS(S50 = Modules!$A$2,Modules!$B$2,S50 = Modules!$A$3,Modules!$B$3,S50 = Modules!$A$4,Modules!$B$4,S50 = Modules!$A$5,Modules!$B$5,S50 = Modules!$A$6,Modules!$B$6,S50 = Modules!$A$7,Modules!$B$7,S50 = Modules!$A$8,Modules!$B$8,S50 = Modules!$A$9,Modules!$B$9,S50 = Modules!$A$10,Modules!$B$10,S50 = Modules!$A$11,Modules!$B$11,S50 = Modules!$A$12,Modules!$B$12, S50 = Modules!$A$13,Modules!$B$13)} -> covid | D50: SEISS | G50: Received | H50: Flag | J50: =CONCATENATE(B50, C50,D50,E50,F50,G50,H50,I50) -> covidSEISSReceivedFlag | K50: Received SEISS TRUE FALSE | L50: Person.java | M50: =IF(OR(O50<>"", Q50<>""),"Yes","No") -> No | S50: Covid
A51: createdByConstructor | C51: {=_xlfn.IFS(S51 = Modules!$A$2,Modules!$B$2,S51 = Modules!$A$3,Modules!$B$3,S51 = Modules!$A$4,Modules!$B$4,S51 = Modules!$A$5,Modules!$B$5,S51 = Modules!$A$6,Modules!$B$6,S51 = Modules!$A$7,Modules!$B$7,S51 = Modules!$A$8,Modules!$B$8,S51 = Modules!$A$9,Modules!$B$9,S51 = Modules!$A$10,Modules!$B$10,S51 = Modules!$A$11,Modules!$B$11,S51 = Modules!$A$12,Modules!$B$12, S51 = Modules!$A$13,Modules!$B$13)} -> dem | D51: CreatedByConstructor | J51: =CONCATENATE(B51, C51,D51,E51,F51,G51,H51,I51) -> demCreatedByConstructor | K51: Variable indicates which constructor used to generate object | L51: BenefitUnit.java | M51: =IF(OR(O51<>"", Q51<>""),"Yes","No") -> No | S51: Demography
A52: dag | C52: {=_xlfn.IFS(S52 = Modules!$A$2,Modules!$B$2,S52 = Modules!$A$3,Modules!$B$3,S52 = Modules!$A$4,Modules!$B$4,S52 = Modules!$A$5,Modules!$B$5,S52 = Modules!$A$6,Modules!$B$6,S52 = Modules!$A$7,Modules!$B$7,S52 = Modules!$A$8,Modules!$B$8,S52 = Modules!$A$9,Modules!$B$9,S52 = Modules!$A$10,Modules!$B$10,S52 = Modules!$A$11,Modules!$B$11,S52 = Modules!$A$12,Modules!$B$12, S52 = Modules!$A$13,Modules!$B$13)} -> dem | D52: Age | J52: =CONCATENATE(B52, C52,D52,E52,F52,G52,H52,I52) -> demAge | K52: Age | L52: Person.java | M52: =IF(OR(O52<>"", Q52<>""),"Yes","No") -> Yes | N52: age_dv | O52: 02_create_ukhls_variables.do | P52: rb080; rx010; pb110 | Q52: 02_00_create_variables_**.do | S52: Demography | U52: Age from age_dv variable. If missing took previous wave's age + 1.
A53: dagpns | C53: {=_xlfn.IFS(S53 = Modules!$A$2,Modules!$B$2,S53 = Modules!$A$3,Modules!$B$3,S53 = Modules!$A$4,Modules!$B$4,S53 = Modules!$A$5,Modules!$B$5,S53 = Modules!$A$6,Modules!$B$6,S53 = Modules!$A$7,Modules!$B$7,S53 = Modules!$A$8,Modules!$B$8,S53 = Modules!$A$9,Modules!$B$9,S53 = Modules!$A$10,Modules!$B$10,S53 = Modules!$A$11,Modules!$B$11,S53 = Modules!$A$12,Modules!$B$12, S53 = Modules!$A$13,Modules!$B$13)} -> dem | D53: Pens | G53: Age | H53: Flag | J53: =CONCATENATE(B53, C53,D53,E53,F53,G53,H53,I53) -> demPensAgeFlag | K53: Individual of state pension age 0 No 1 Yes | M53: =IF(OR(O53<>"", Q53<>""),"Yes","No") -> Yes | P53: dgn (rb090); dag (rb080; rx010; pb110); stm (pb100) | Q53: 02_00_create_variables_**.do | S53: Demography
A54: dagpns_sp | C54: {=_xlfn.IFS(S54 = Modules!$A$2,Modules!$B$2,S54 = Modules!$A$3,Modules!$B$3,S54 = Modules!$A$4,Modules!$B$4,S54 = Modules!$A$5,Modules!$B$5,S54 = Modules!$A$6,Modules!$B$6,S54 = Modules!$A$7,Modules!$B$7,S54 = Modules!$A$8,Modules!$B$8,S54 = Modules!$A$9,Modules!$B$9,S54 = Modules!$A$10,Modules!$B$10,S54 = Modules!$A$11,Modules!$B$11,S54 = Modules!$A$12,Modules!$B$12, S54 = Modules!$A$13,Modules!$B$13)} -> dem | D54: Pens | E54: Partner | G54: Age | H54: Flag | J54: =CONCATENATE(B54, C54,D54,E54,F54,G54,H54,I54) -> demPensPartnerAgeFlag | K54: Partner of state pension age 0 No 1 Yes | M54: =IF(OR(O54<>"", Q54<>""),"Yes","No") -> Yes | P54: dgn (rb090); dag (rb080; rx010; pb110); stm (pb100); idpartner (rb240; urtgrp) | Q54: 02_00_create_variables_**.do | S54: Demography
A55: dagpns_y | C55: {=_xlfn.IFS(S55 = Modules!$A$2,Modules!$B$2,S55 = Modules!$A$3,Modules!$B$3,S55 = Modules!$A$4,Modules!$B$4,S55 = Modules!$A$5,Modules!$B$5,S55 = Modules!$A$6,Modules!$B$6,S55 = Modules!$A$7,Modules!$B$7,S55 = Modules!$A$8,Modules!$B$8,S55 = Modules!$A$9,Modules!$B$9,S55 = Modules!$A$10,Modules!$B$10,S55 = Modules!$A$11,Modules!$B$11,S55 = Modules!$A$12,Modules!$B$12, S55 = Modules!$A$13,Modules!$B$13)} -> dem | D55: Pens | F55: Enter | G55: Age | H55: Flag | J55: =CONCATENATE(B55, C55,D55,E55,F55,G55,H55,I55) -> demPensEnterAgeFlag | K55: Year individual reaches the state pension age 0 No 1 Yes | M55: =IF(OR(O55<>"", Q55<>""),"Yes","No") -> Yes | P55: dgn (rb090); dag (rb080; rx010; pb110); stm (pb100) | Q55: 02_00_create_variables_**.do | S55: Demography
A56: dagpns_y_sp | C56: {=_xlfn.IFS(S56 = Modules!$A$2,Modules!$B$2,S56 = Modules!$A$3,Modules!$B$3,S56 = Modules!$A$4,Modules!$B$4,S56 = Modules!$A$5,Modules!$B$5,S56 = Modules!$A$6,Modules!$B$6,S56 = Modules!$A$7,Modules!$B$7,S56 = Modules!$A$8,Modules!$B$8,S56 = Modules!$A$9,Modules!$B$9,S56 = Modules!$A$10,Modules!$B$10,S56 = Modules!$A$11,Modules!$B$11,S56 = Modules!$A$12,Modules!$B$12, S56 = Modules!$A$13,Modules!$B$13)} -> dem | D56: Pens | E56: Partner | F56: Enter | G56: Age | H56: Flag | J56: =CONCATENATE(B56, C56,D56,E56,F56,G56,H56,I56) -> demPensPartnerEnterAgeFlag | K56: Year partner reaches the state pension age 0 No 1 Yes | M56: =IF(OR(O56<>"", Q56<>""),"Yes","No") -> Yes | P56: dgn (rb090); dag (rb080; rx010; pb110); stm (pb100); idpartner (rb240; urtgrp) | Q56: 02_00_create_variables_**.do | S56: Demography
A57: dagpns_y1 | C57: {=_xlfn.IFS(S57 = Modules!$A$2,Modules!$B$2,S57 = Modules!$A$3,Modules!$B$3,S57 = Modules!$A$4,Modules!$B$4,S57 = Modules!$A$5,Modules!$B$5,S57 = Modules!$A$6,Modules!$B$6,S57 = Modules!$A$7,Modules!$B$7,S57 = Modules!$A$8,Modules!$B$8,S57 = Modules!$A$9,Modules!$B$9,S57 = Modules!$A$10,Modules!$B$10,S57 = Modules!$A$11,Modules!$B$11,S57 = Modules!$A$12,Modules!$B$12, S57 = Modules!$A$13,Modules!$B$13)} -> dem | D57: Pens | F57: Enter | G57: Age | H57: Flag | I57: L1 | J57: =CONCATENATE(B57, C57,D57,E57,F57,G57,H57,I57) -> demPensEnterAgeFlagL1 | K57: Lag(1) of dagpns_y | M57: =IF(OR(O57<>"", Q57<>""),"Yes","No") -> Yes | P57: dgn (rb090); dag (rb080; rx010; pb110); stm (pb100) | Q57: 02_00_create_variables_**.do | S57: Demography
A58: dagpns_y1_sp | C58: {=_xlfn.IFS(S58 = Modules!$A$2,Modules!$B$2,S58 = Modules!$A$3,Modules!$B$3,S58 = Modules!$A$4,Modules!$B$4,S58 = Modules!$A$5,Modules!$B$5,S58 = Modules!$A$6,Modules!$B$6,S58 = Modules!$A$7,Modules!$B$7,S58 = Modules!$A$8,Modules!$B$8,S58 = Modules!$A$9,Modules!$B$9,S58 = Modules!$A$10,Modules!$B$10,S58 = Modules!$A$11,Modules!$B$11,S58 = Modules!$A$12,Modules!$B$12, S58 = Modules!$A$13,Modules!$B$13)} -> dem | D58: Pens | E58: Partner | F58: Enter | G58: Age | H58: Flag | I58: L1 | J58: =CONCATENATE(B58, C58,D58,E58,F58,G58,H58,I58) -> demPensPartnerEnterAgeFlagL1 | K58: Lag(1) of dagpns_y_sp | M58: =IF(OR(O58<>"", Q58<>""),"Yes","No") -> Yes | P58: dgn (rb090); dag (rb080; rx010; pb110); stm (pb100); idpartner (rb240; urtgrp) | Q58: 02_00_create_variables_**.do | S58: Demography
A59: dagsp | C59: {=_xlfn.IFS(S59 = Modules!$A$2,Modules!$B$2,S59 = Modules!$A$3,Modules!$B$3,S59 = Modules!$A$4,Modules!$B$4,S59 = Modules!$A$5,Modules!$B$5,S59 = Modules!$A$6,Modules!$B$6,S59 = Modules!$A$7,Modules!$B$7,S59 = Modules!$A$8,Modules!$B$8,S59 = Modules!$A$9,Modules!$B$9,S59 = Modules!$A$10,Modules!$B$10,S59 = Modules!$A$11,Modules!$B$11,S59 = Modules!$A$12,Modules!$B$12, S59 = Modules!$A$13,Modules!$B$13)} -> dem | D59: Age | E59: Partner | J59: =CONCATENATE(B59, C59,D59,E59,F59,G59,H59,I59) -> demAgePartner | K59: Partner's age | L59: Initial Populations | M59: =IF(OR(O59<>"", Q59<>""),"Yes","No") -> Yes | N59: dag (age_dv); idpartner | O59: 02_create_ukhls_variables.do | P59: dag (rb080, rx010, pb110); idpartner (rb240, urtgrp) | S59: Demography
A60: dagsq | C60: {=_xlfn.IFS(S60 = Modules!$A$2,Modules!$B$2,S60 = Modules!$A$3,Modules!$B$3,S60 = Modules!$A$4,Modules!$B$4,S60 = Modules!$A$5,Modules!$B$5,S60 = Modules!$A$6,Modules!$B$6,S60 = Modules!$A$7,Modules!$B$7,S60 = Modules!$A$8,Modules!$B$8,S60 = Modules!$A$9,Modules!$B$9,S60 = Modules!$A$10,Modules!$B$10,S60 = Modules!$A$11,Modules!$B$11,S60 = Modules!$A$12,Modules!$B$12, S60 = Modules!$A$13,Modules!$B$13)} -> dem | D60: Age | H60: Sq | J60: =CONCATENATE(B60, C60,D60,E60,F60,G60,H60,I60) -> demAgeSq | K60: Age Squared | L60: Person.java | M60: =IF(OR(O60<>"", Q60<>""),"Yes","No") -> Yes | N60: age_dv | O60: 02_create_ukhls_variables.do | S60: Demography | U60: Age sqared from age_dv variable.
A61: daughter_socare_hrs | C61: {=_xlfn.IFS(S61 = Modules!$A$2,Modules!$B$2,S61 = Modules!$A$3,Modules!$B$3,S61 = Modules!$A$4,Modules!$B$4,S61 = Modules!$A$5,Modules!$B$5,S61 = Modules!$A$6,Modules!$B$6,S61 = Modules!$A$7,Modules!$B$7,S61 = Modules!$A$8,Modules!$B$8,S61 = Modules!$A$9,Modules!$B$9,S61 = Modules!$A$10,Modules!$B$10,S61 = Modules!$A$11,Modules!$B$11,S61 = Modules!$A$12,Modules!$B$12, S61 = Modules!$A$13,Modules!$B$13)} -> care | D61: Hrs | G61: FromDaughter | J61: =CONCATENATE(B61, C61,D61,E61,F61,G61,H61,I61) -> careHrsFromDaughter | K61: Hours of social care received from the daughter | L61: Person.java | M61: =IF(OR(O61<>"", Q61<>""),"Yes","No") -> Yes | N61: helpcode; hrs | O61: 03_social_care_received | S61: Social care
A62: dchpd | C62: {=_xlfn.IFS(S62 = Modules!$A$2,Modules!$B$2,S62 = Modules!$A$3,Modules!$B$3,S62 = Modules!$A$4,Modules!$B$4,S62 = Modules!$A$5,Modules!$B$5,S62 = Modules!$A$6,Modules!$B$6,S62 = Modules!$A$7,Modules!$B$7,S62 = Modules!$A$8,Modules!$B$8,S62 = Modules!$A$9,Modules!$B$9,S62 = Modules!$A$10,Modules!$B$10,S62 = Modules!$A$11,Modules!$B$11,S62 = Modules!$A$12,Modules!$B$12, S62 = Modules!$A$13,Modules!$B$13)} -> dem | D62: NChild | G62: 0 | J62: =CONCATENATE(B62, C62,D62,E62,F62,G62,H62,I62) -> demNChild0 | K62: Number of dependent children born in the last year | M62: =IF(OR(O62<>"", Q62<>""),"Yes","No") -> Yes | P62: dag (rb080; rx010; pb110); idmother (rb230; urtgrp); dgn (rb090) | Q62: 02_00_create_variables_**.do | S62: Demography
A63: dcpagdf | C63: {=_xlfn.IFS(S63 = Modules!$A$2,Modules!$B$2,S63 = Modules!$A$3,Modules!$B$3,S63 = Modules!$A$4,Modules!$B$4,S63 = Modules!$A$5,Modules!$B$5,S63 = Modules!$A$6,Modules!$B$6,S63 = Modules!$A$7,Modules!$B$7,S63 = Modules!$A$8,Modules!$B$8,S63 = Modules!$A$9,Modules!$B$9,S63 = Modules!$A$10,Modules!$B$10,S63 = Modules!$A$11,Modules!$B$11,S63 = Modules!$A$12,Modules!$B$12, S63 = Modules!$A$13,Modules!$B$13)} -> dem | D63: Age | E63: Partner | G63: Diff | J63: =CONCATENATE(B63, C63,D63,E63,F63,G63,H63,I63) -> demAgePartnerDiff | K63: Difference between ages of partners in a union | L63: Person.java | M63: =IF(OR(O63<>"", Q63<>""),"Yes","No") -> Yes | N63: dag (age_dv); dagsp | O63: 02_create_ukhls_variables.do | P63: dag(rb080; rx010; pb110) | Q63: 02_00_create_variables_**.do | S63: Demography | U63: Generated from age_dv variable, subtracting spouse's age from own.
A64: dcpagdf_lag1 | C64: {=_xlfn.IFS(S64 = Modules!$A$2,Modules!$B$2,S64 = Modules!$A$3,Modules!$B$3,S64 = Modules!$A$4,Modules!$B$4,S64 = Modules!$A$5,Modules!$B$5,S64 = Modules!$A$6,Modules!$B$6,S64 = Modules!$A$7,Modules!$B$7,S64 = Modules!$A$8,Modules!$B$8,S64 = Modules!$A$9,Modules!$B$9,S64 = Modules!$A$10,Modules!$B$10,S64 = Modules!$A$11,Modules!$B$11,S64 = Modules!$A$12,Modules!$B$12, S64 = Modules!$A$13,Modules!$B$13)} -> dem | D64: Age | E64: Partner | G64: Diff | I64: L1 | J64: =CONCATENATE(B64, C64,D64,E64,F64,G64,H64,I64) -> demAgePartnerDiffL1 | K64: Lag(1) of dcpagdf | L64: Person.java | M64: =IF(OR(O64<>"", Q64<>""),"Yes","No") -> No | S64: Demography
A65: dcpen | C65: {=_xlfn.IFS(S65 = Modules!$A$2,Modules!$B$2,S65 = Modules!$A$3,Modules!$B$3,S65 = Modules!$A$4,Modules!$B$4,S65 = Modules!$A$5,Modules!$B$5,S65 = Modules!$A$6,Modules!$B$6,S65 = Modules!$A$7,Modules!$B$7,S65 = Modules!$A$8,Modules!$B$8,S65 = Modules!$A$9,Modules!$B$9,S65 = Modules!$A$10,Modules!$B$10,S65 = Modules!$A$11,Modules!$B$11,S65 = Modules!$A$12,Modules!$B$12, S65 = Modules!$A$13,Modules!$B$13)} -> dem | D65: Enter | E65: Partner | H65: Flag | J65: =CONCATENATE(B65, C65,D65,E65,F65,G65,H65,I65) -> demEnterPartnerFlag | K65: Enter partnership 0 No 1 Yes | L65: Initial Populations | M65: =IF(OR(O65<>"", Q65<>""),"Yes","No") -> Yes | N65: dcpst (mastat_dv) | O65: 02_create_ukhls_variables.do | P65: dcpst (idpartner (rb240, urtgrp)) | Q65: 02_00_create_variables_**.do | S65: Demography | U65: Generated from mastat_dv variable, 1 means that individual has entered a partnership (2/3/10=married/civil partnership/cohabiting), when their previous wave's mastat_dv was 1=single or 4-9=previously partnered. In cases where mastat_dv was the same but ppid at t-1 was not equal to ppid at t then set to 1.
A66: dcpex | C66: {=_xlfn.IFS(S66 = Modules!$A$2,Modules!$B$2,S66 = Modules!$A$3,Modules!$B$3,S66 = Modules!$A$4,Modules!$B$4,S66 = Modules!$A$5,Modules!$B$5,S66 = Modules!$A$6,Modules!$B$6,S66 = Modules!$A$7,Modules!$B$7,S66 = Modules!$A$8,Modules!$B$8,S66 = Modules!$A$9,Modules!$B$9,S66 = Modules!$A$10,Modules!$B$10,S66 = Modules!$A$11,Modules!$B$11,S66 = Modules!$A$12,Modules!$B$12, S66 = Modules!$A$13,Modules!$B$13)} -> dem | D66: Exit | E66: Partner | H66: Flag | J66: =CONCATENATE(B66, C66,D66,E66,F66,G66,H66,I66) -> demExitPartnerFlag | K66: Exited partnership 0 No 1 Yes | L66: Initial Populations | M66: =IF(OR(O66<>"", Q66<>""),"Yes","No") -> Yes | N66: dcpst (mastat_dv) | O66: 02_create_ukhls_variables.do | P66: dcpst (idpartner (rb240, urtgrp)) | Q66: 02_00_create_variables_**.do | S66: Demography | U66: Generated from mastat_dv variable, 1 means that individual has exited a partnership (mastat_dv = 1,4,5,7,8), when they were in a relationship in the previous wave (mastat_dv=2/3/10). Excluded those who exited a partnership due to widowhood. In cases where mastat_dv was the same but ppid at t-1 was not equal to ppid at t then set to 1.
A67: dcpst | C67: {=_xlfn.IFS(S67 = Modules!$A$2,Modules!$B$2,S67 = Modules!$A$3,Modules!$B$3,S67 = Modules!$A$4,Modules!$B$4,S67 = Modules!$A$5,Modules!$B$5,S67 = Modules!$A$6,Modules!$B$6,S67 = Modules!$A$7,Modules!$B$7,S67 = Modules!$A$8,Modules!$B$8,S67 = Modules!$A$9,Modules!$B$9,S67 = Modules!$A$10,Modules!$B$10,S67 = Modules!$A$11,Modules!$B$11,S67 = Modules!$A$12,Modules!$B$12, S67 = Modules!$A$13,Modules!$B$13)} -> dem | E67: Partner | F67: Status | J67: =CONCATENATE(B67, C67,D67,E67,F67,G67,H67,I67) -> demPartnerStatus | K67: Partnership status 1 Partnered 2 Single and never married 3 Previously partnered | L67: Person.java | M67: =IF(OR(O67<>"", Q67<>""),"Yes","No") -> Yes | N67: mastat_dv | O67: 02_create_ukhls_variables.do | P67: idpartner (rb240, urtgrp) | Q67: 02_00_create_variables_**.do | S67: Demography | U67: Partnership status from mastat_dv variable. 1 (Partnered) are those in marriages or cohabiting relationships, 2 (Single) are those who have never been married, 3 (Previously partnered) Individuals who have been in a formal relationship, i.e. married or civil partnership.
A68: dcpst_lag1 | C68: {=_xlfn.IFS(S68 = Modules!$A$2,Modules!$B$2,S68 = Modules!$A$3,Modules!$B$3,S68 = Modules!$A$4,Modules!$B$4,S68 = Modules!$A$5,Modules!$B$5,S68 = Modules!$A$6,Modules!$B$6,S68 = Modules!$A$7,Modules!$B$7,S68 = Modules!$A$8,Modules!$B$8,S68 = Modules!$A$9,Modules!$B$9,S68 = Modules!$A$10,Modules!$B$10,S68 = Modules!$A$11,Modules!$B$11,S68 = Modules!$A$12,Modules!$B$12, S68 = Modules!$A$13,Modules!$B$13)} -> dem | E68: Partner | F68: Status | I68: L1 | J68: =CONCATENATE(B68, C68,D68,E68,F68,G68,H68,I68) -> demPartnerStatusL1 | K68: Lag(1) of dcpst | L68: Person.java | M68: =IF(OR(O68<>"", Q68<>""),"Yes","No") -> No | S68: Demography
A69: dcpst_lag2 | C69: {=_xlfn.IFS(S69 = Modules!$A$2,Modules!$B$2,S69 = Modules!$A$3,Modules!$B$3,S69 = Modules!$A$4,Modules!$B$4,S69 = Modules!$A$5,Modules!$B$5,S69 = Modules!$A$6,Modules!$B$6,S69 = Modules!$A$7,Modules!$B$7,S69 = Modules!$A$8,Modules!$B$8,S69 = Modules!$A$9,Modules!$B$9,S69 = Modules!$A$10,Modules!$B$10,S69 = Modules!$A$11,Modules!$B$11,S69 = Modules!$A$12,Modules!$B$12, S69 = Modules!$A$13,Modules!$B$13)} -> dem | E69: Partner | F69: Status | I69: L2 | J69: =CONCATENATE(B69, C69,D69,E69,F69,G69,H69,I69) -> demPartnerStatusL2 | K69: Lag(2) of dcpst | L69: Person.java | M69: =IF(OR(O69<>"", Q69<>""),"Yes","No") -> No | S69: Demography
A70: dcpstLocal | B70: i_ | C70: {=_xlfn.IFS(S70 = Modules!$A$2,Modules!$B$2,S70 = Modules!$A$3,Modules!$B$3,S70 = Modules!$A$4,Modules!$B$4,S70 = Modules!$A$5,Modules!$B$5,S70 = Modules!$A$6,Modules!$B$6,S70 = Modules!$A$7,Modules!$B$7,S70 = Modules!$A$8,Modules!$B$8,S70 = Modules!$A$9,Modules!$B$9,S70 = Modules!$A$10,Modules!$B$10,S70 = Modules!$A$11,Modules!$B$11,S70 = Modules!$A$12,Modules!$B$12, S70 = Modules!$A$13,Modules!$B$13)} -> dem | E70: Partner | F70: Status | J70: =CONCATENATE(B70, C70,D70,E70,F70,G70,H70,I70) -> i_demPartnerStatus | K70: Partnership status local | L70: Person.java | M70: =IF(OR(O70<>"", Q70<>""),"Yes","No") -> No | S70: Demography | U70: Local variables interact with regression models
A71: dcpyy | C71: {=_xlfn.IFS(S71 = Modules!$A$2,Modules!$B$2,S71 = Modules!$A$3,Modules!$B$3,S71 = Modules!$A$4,Modules!$B$4,S71 = Modules!$A$5,Modules!$B$5,S71 = Modules!$A$6,Modules!$B$6,S71 = Modules!$A$7,Modules!$B$7,S71 = Modules!$A$8,Modules!$B$8,S71 = Modules!$A$9,Modules!$B$9,S71 = Modules!$A$10,Modules!$B$10,S71 = Modules!$A$11,Modules!$B$11,S71 = Modules!$A$12,Modules!$B$12, S71 = Modules!$A$13,Modules!$B$13)} -> dem | E71: Partner | F71: NYear | J71: =CONCATENATE(B71, C71,D71,E71,F71,G71,H71,I71) -> demPartnerNYear | K71: Years in partnership | L71: Person.java | M71: =IF(OR(O71<>"", Q71<>""),"Yes","No") -> Yes | N71: idpartner (ppid) | O71: 02_create_ukhls_variables.do | P71: idpartner (rb240, urtgrp) | Q71: 02_00_create_variables_**.do | S71: Demography | U71: Generated from dep variable for each year in the same partnership this variable increases by one. | V71: *
A72: dcpyy_lag1 | C72: {=_xlfn.IFS(S72 = Modules!$A$2,Modules!$B$2,S72 = Modules!$A$3,Modules!$B$3,S72 = Modules!$A$4,Modules!$B$4,S72 = Modules!$A$5,Modules!$B$5,S72 = Modules!$A$6,Modules!$B$6,S72 = Modules!$A$7,Modules!$B$7,S72 = Modules!$A$8,Modules!$B$8,S72 = Modules!$A$9,Modules!$B$9,S72 = Modules!$A$10,Modules!$B$10,S72 = Modules!$A$11,Modules!$B$11,S72 = Modules!$A$12,Modules!$B$12, S72 = Modules!$A$13,Modules!$B$13)} -> dem | E72: Partner | F72: NYear | I72: L1 | J72: =CONCATENATE(B72, C72,D72,E72,F72,G72,H72,I72) -> demPartnerNYearL1 | K72: Lag(1) of dcpyy | L72: Person.java | M72: =IF(OR(O72<>"", Q72<>""),"Yes","No") -> No | S72: Demography
A73: dct | C73: {=_xlfn.IFS(S73 = Modules!$A$2,Modules!$B$2,S73 = Modules!$A$3,Modules!$B$3,S73 = Modules!$A$4,Modules!$B$4,S73 = Modules!$A$5,Modules!$B$5,S73 = Modules!$A$6,Modules!$B$6,S73 = Modules!$A$7,Modules!$B$7,S73 = Modules!$A$8,Modules!$B$8,S73 = Modules!$A$9,Modules!$B$9,S73 = Modules!$A$10,Modules!$B$10,S73 = Modules!$A$11,Modules!$B$11,S73 = Modules!$A$12,Modules!$B$12, S73 = Modules!$A$13,Modules!$B$13)} -> dem | D73: Country | J73: =CONCATENATE(B73, C73,D73,E73,F73,G73,H73,I73) -> demCountry | K73: Country | L73: Country.java | M73: =IF(OR(O73<>"", Q73<>""),"Yes","No") -> Yes | O73: 02_create_ukhls_variables.do | P73: pl030; pl031; pl032; idperson (upid) | Q73: 02_00_create_variables_**.do | S73: Demography | U73: Set to 15 for the UK for observations from UKHLS.
A74: ded | C74: {=_xlfn.IFS(S74 = Modules!$A$2,Modules!$B$2,S74 = Modules!$A$3,Modules!$B$3,S74 = Modules!$A$4,Modules!$B$4,S74 = Modules!$A$5,Modules!$B$5,S74 = Modules!$A$6,Modules!$B$6,S74 = Modules!$A$7,Modules!$B$7,S74 = Modules!$A$8,Modules!$B$8,S74 = Modules!$A$9,Modules!$B$9,S74 = Modules!$A$10,Modules!$B$10,S74 = Modules!$A$11,Modules!$B$11,S74 = Modules!$A$12,Modules!$B$12, S74 = Modules!$A$13,Modules!$B$13)} -> edu | D74: Spell | H74: Flag | J74: =CONCATENATE(B74, C74,D74,E74,F74,G74,H74,I74) -> eduSpellFlag | K74: In Continuous Education 0 No 1 Yes | L74: Person.java | M74: =IF(OR(O74<>"", Q74<>""),"Yes","No") -> Yes | N74: jbstat | O74: 02_create_ukhls_variables.do | P74: dag (rb080; rx010; pb110), les_c3 (pl030; pl031; pl032; rb210; rb211) | Q74: 02_00_create_variables_**.do | S74: Education | U74: In education from jbstat variable, where jbstat = 7 then in education. If missing then used previous or next wave's labour force status and dates left education to fill in. If have returned to education following a break then ded = 0.
A75: deh_c3 | C75: {=_xlfn.IFS(S75 = Modules!$A$2,Modules!$B$2,S75 = Modules!$A$3,Modules!$B$3,S75 = Modules!$A$4,Modules!$B$4,S75 = Modules!$A$5,Modules!$B$5,S75 = Modules!$A$6,Modules!$B$6,S75 = Modules!$A$7,Modules!$B$7,S75 = Modules!$A$8,Modules!$B$8,S75 = Modules!$A$9,Modules!$B$9,S75 = Modules!$A$10,Modules!$B$10,S75 = Modules!$A$11,Modules!$B$11,S75 = Modules!$A$12,Modules!$B$12, S75 = Modules!$A$13,Modules!$B$13)} -> edu | D75: Highest | H75: C3 | J75: =CONCATENATE(B75, C75,D75,E75,F75,G75,H75,I75) -> eduHighestC3 | K75: Education - Highest Status 1 High 2 Medium 3 Low | L75: Person.java | M75: =IF(OR(O75<>"", Q75<>""),"Yes","No") -> Yes | N75: hiqual_dv | O75: 02_create_ukhls_variables.do | P75: pe040; pe041 | Q75: 02_00_create_variables_**.do | S75: Education | U75: Education from hiqual_dv variable. 1 (High) education means degree, 2 (Medium) education means Other higher degree, A-levels etc., GCSE etc., 3 (Low) means Other qualification, no qualification.
A76: deh_c3_lag1 | C76: {=_xlfn.IFS(S76 = Modules!$A$2,Modules!$B$2,S76 = Modules!$A$3,Modules!$B$3,S76 = Modules!$A$4,Modules!$B$4,S76 = Modules!$A$5,Modules!$B$5,S76 = Modules!$A$6,Modules!$B$6,S76 = Modules!$A$7,Modules!$B$7,S76 = Modules!$A$8,Modules!$B$8,S76 = Modules!$A$9,Modules!$B$9,S76 = Modules!$A$10,Modules!$B$10,S76 = Modules!$A$11,Modules!$B$11,S76 = Modules!$A$12,Modules!$B$12, S76 = Modules!$A$13,Modules!$B$13)} -> edu | D76: Highest | H76: C3 | I76: L1 | J76: =CONCATENATE(B76, C76,D76,E76,F76,G76,H76,I76) -> eduHighestC3L1 | K76: Lag(1) of deh | L76: Person.java | M76: =IF(OR(O76<>"", Q76<>""),"Yes","No") -> No | S76: Education
A77: deh_c3Local | B77: i_ | C77: {=_xlfn.IFS(S77 = Modules!$A$2,Modules!$B$2,S77 = Modules!$A$3,Modules!$B$3,S77 = Modules!$A$4,Modules!$B$4,S77 = Modules!$A$5,Modules!$B$5,S77 = Modules!$A$6,Modules!$B$6,S77 = Modules!$A$7,Modules!$B$7,S77 = Modules!$A$8,Modules!$B$8,S77 = Modules!$A$9,Modules!$B$9,S77 = Modules!$A$10,Modules!$B$10,S77 = Modules!$A$11,Modules!$B$11,S77 = Modules!$A$12,Modules!$B$12, S77 = Modules!$A$13,Modules!$B$13)} -> edu | D77: Highest | H77: C3 | J77: =CONCATENATE(B77, C77,D77,E77,F77,G77,H77,I77) -> i_eduHighestC3 | K77: Education - Highest Status local | L77: BenefitUnit.java | M77: =IF(OR(O77<>"", Q77<>""),"Yes","No") -> No | S77: Education
A78: dehf_c3 | C78: {=_xlfn.IFS(S78 = Modules!$A$2,Modules!$B$2,S78 = Modules!$A$3,Modules!$B$3,S78 = Modules!$A$4,Modules!$B$4,S78 = Modules!$A$5,Modules!$B$5,S78 = Modules!$A$6,Modules!$B$6,S78 = Modules!$A$7,Modules!$B$7,S78 = Modules!$A$8,Modules!$B$8,S78 = Modules!$A$9,Modules!$B$9,S78 = Modules!$A$10,Modules!$B$10,S78 = Modules!$A$11,Modules!$B$11,S78 = Modules!$A$12,Modules!$B$12, S78 = Modules!$A$13,Modules!$B$13)} -> edu | D78: Highest | E78: Father | H78: C3 | J78: =CONCATENATE(B78, C78,D78,E78,F78,G78,H78,I78) -> eduHighestFatherC3 | K78: Education - Father's Highest Status 1 High 2 Medium 3 Low | L78: Person.java | M78: =IF(OR(O78<>"", Q78<>""),"Yes","No") -> Yes | N78: paedqf | O78: 02_create_ukhls_variables.do | S78: Education | U78: Father's education form paedqf in xwavedat file. Same rules as for dehm above.
A79: dehm_c3 | C79: {=_xlfn.IFS(S79 = Modules!$A$2,Modules!$B$2,S79 = Modules!$A$3,Modules!$B$3,S79 = Modules!$A$4,Modules!$B$4,S79 = Modules!$A$5,Modules!$B$5,S79 = Modules!$A$6,Modules!$B$6,S79 = Modules!$A$7,Modules!$B$7,S79 = Modules!$A$8,Modules!$B$8,S79 = Modules!$A$9,Modules!$B$9,S79 = Modules!$A$10,Modules!$B$10,S79 = Modules!$A$11,Modules!$B$11,S79 = Modules!$A$12,Modules!$B$12, S79 = Modules!$A$13,Modules!$B$13)} -> edu | D79: Highest | E79: Mother | H79: C3 | J79: =CONCATENATE(B79, C79,D79,E79,F79,G79,H79,I79) -> eduHighestMotherC3 | K79: Education - Mother's Highest Status 1 High 2 Medium 3 Low | L79: Person.java | M79: =IF(OR(O79<>"", Q79<>""),"Yes","No") -> Yes | N79: maedqf | O79: 02_create_ukhls_variables.do | S79: Education | U79: Mother's education from maedqf in xwavedat file. If missing and individual lives with parents, their current level of education is used to fill in missing values. Levels set to match deh variable, 1 (High) is "she gained a university degree or higher degree", 2 (Medium) is "she gained post school quals or certs (e.g. city & guilds)" or "she left school with some qualifications or certificates" and 3 (Low) is "she left school with no qualifications or certificates" or "she did not go to school at all" or "other".
A80: dehsp_c3 | C80: {=_xlfn.IFS(S80 = Modules!$A$2,Modules!$B$2,S80 = Modules!$A$3,Modules!$B$3,S80 = Modules!$A$4,Modules!$B$4,S80 = Modules!$A$5,Modules!$B$5,S80 = Modules!$A$6,Modules!$B$6,S80 = Modules!$A$7,Modules!$B$7,S80 = Modules!$A$8,Modules!$B$8,S80 = Modules!$A$9,Modules!$B$9,S80 = Modules!$A$10,Modules!$B$10,S80 = Modules!$A$11,Modules!$B$11,S80 = Modules!$A$12,Modules!$B$12, S80 = Modules!$A$13,Modules!$B$13)} -> edu | D80: Highest | E80: Partner | H80: C3 | J80: =CONCATENATE(B80, C80,D80,E80,F80,G80,H80,I80) -> eduHighestPartnerC3 | K80: Education - Spouse's Highest Status 1 High 2 Medium 3 Low | L80: Person.java | M80: =IF(OR(O80<>"", Q80<>""),"Yes","No") -> Yes | N80: hiqual_dv | O80: 02_create_ukhls_variables.do | P80: pe040; pe041; idpartner (rb240, urtgrp) | Q80: 02_00_create_variables_**.do | S80: Education | U80: Spouse's education from hiqual_dv variable. 1 (High) education means degree, 2 (Medium) education means Other higher degree, A-levels etc., GCSE etc., 3 (Low) means Other qualification, no qualification.
A81: dehsp_c3_lag1 | C81: {=_xlfn.IFS(S81 = Modules!$A$2,Modules!$B$2,S81 = Modules!$A$3,Modules!$B$3,S81 = Modules!$A$4,Modules!$B$4,S81 = Modules!$A$5,Modules!$B$5,S81 = Modules!$A$6,Modules!$B$6,S81 = Modules!$A$7,Modules!$B$7,S81 = Modules!$A$8,Modules!$B$8,S81 = Modules!$A$9,Modules!$B$9,S81 = Modules!$A$10,Modules!$B$10,S81 = Modules!$A$11,Modules!$B$11,S81 = Modules!$A$12,Modules!$B$12, S81 = Modules!$A$13,Modules!$B$13)} -> edu | D81: Highest | E81: Partner | H81: C3 | I81: L1 | J81: =CONCATENATE(B81, C81,D81,E81,F81,G81,H81,I81) -> eduHighestPartnerC3L1 | K81: Lag(1) of dehsp | L81: Person.java | M81: =IF(OR(O81<>"", Q81<>""),"Yes","No") -> No | S81: Education
A82: der | C82: {=_xlfn.IFS(S82 = Modules!$A$2,Modules!$B$2,S82 = Modules!$A$3,Modules!$B$3,S82 = Modules!$A$4,Modules!$B$4,S82 = Modules!$A$5,Modules!$B$5,S82 = Modules!$A$6,Modules!$B$6,S82 = Modules!$A$7,Modules!$B$7,S82 = Modules!$A$8,Modules!$B$8,S82 = Modules!$A$9,Modules!$B$9,S82 = Modules!$A$10,Modules!$B$10,S82 = Modules!$A$11,Modules!$B$11,S82 = Modules!$A$12,Modules!$B$12, S82 = Modules!$A$13,Modules!$B$13)} -> edu | D82: Return | H82: Flag | J82: =CONCATENATE(B82, C82,D82,E82,F82,G82,H82,I82) -> eduReturnFlag | K82: Return to Education 0 No 1 Yes | L82: Person.java | M82: =IF(OR(O82<>"", Q82<>""),"Yes","No") -> Yes | N82: jbstat | O82: 02_create_ukhls_variables.do | P82: ded (pe040; pe041); les_c3 (pl030; pl031; pl032; rb210; rb211) | Q82: 02_00_create_variables_**.do | S82: Education | U82: In education after having taken a break from jbstat variable, where jbstat = 7 and previous wave's jbstat ne 7 then returned to education. If missing then used previous or next wave's labour force status and dates left education to fill in.
A83: desiredAgeDiff | C83: {=_xlfn.IFS(S83 = Modules!$A$2,Modules!$B$2,S83 = Modules!$A$3,Modules!$B$3,S83 = Modules!$A$4,Modules!$B$4,S83 = Modules!$A$5,Modules!$B$5,S83 = Modules!$A$6,Modules!$B$6,S83 = Modules!$A$7,Modules!$B$7,S83 = Modules!$A$8,Modules!$B$8,S83 = Modules!$A$9,Modules!$B$9,S83 = Modules!$A$10,Modules!$B$10,S83 = Modules!$A$11,Modules!$B$11,S83 = Modules!$A$12,Modules!$B$12, S83 = Modules!$A$13,Modules!$B$13)} -> dem | D83: Age | G83: DiffDesired | J83: =CONCATENATE(B83, C83,D83,E83,F83,G83,H83,I83) -> demAgeDiffDesired | K83: Target age difference between prospective spouses | L83: Person.java | M83: =IF(OR(O83<>"", Q83<>""),"Yes","No") -> No | S83: Demography
A84: desiredEarningsPotentialDiff | C84: {=_xlfn.IFS(S84 = Modules!$A$2,Modules!$B$2,S84 = Modules!$A$3,Modules!$B$3,S84 = Modules!$A$4,Modules!$B$4,S84 = Modules!$A$5,Modules!$B$5,S84 = Modules!$A$6,Modules!$B$6,S84 = Modules!$A$7,Modules!$B$7,S84 = Modules!$A$8,Modules!$B$8,S84 = Modules!$A$9,Modules!$B$9,S84 = Modules!$A$10,Modules!$B$10,S84 = Modules!$A$11,Modules!$B$11,S84 = Modules!$A$12,Modules!$B$12, S84 = Modules!$A$13,Modules!$B$13)} -> y | D84: Wage | G84: Desired | J84: =CONCATENATE(B84, C84,D84,E84,F84,G84,H84,I84) -> yWageDesired | K84: Target difference between earnings potentials of prospective partners | L84: Person.java | M84: =IF(OR(O84<>"", Q84<>""),"Yes","No") -> No | S84: Income
A85: dgn | C85: {=_xlfn.IFS(S85 = Modules!$A$2,Modules!$B$2,S85 = Modules!$A$3,Modules!$B$3,S85 = Modules!$A$4,Modules!$B$4,S85 = Modules!$A$5,Modules!$B$5,S85 = Modules!$A$6,Modules!$B$6,S85 = Modules!$A$7,Modules!$B$7,S85 = Modules!$A$8,Modules!$B$8,S85 = Modules!$A$9,Modules!$B$9,S85 = Modules!$A$10,Modules!$B$10,S85 = Modules!$A$11,Modules!$B$11,S85 = Modules!$A$12,Modules!$B$12, S85 = Modules!$A$13,Modules!$B$13)} -> dem | D85: Male | H85: Flag | J85: =CONCATENATE(B85, C85,D85,E85,F85,G85,H85,I85) -> demMaleFlag | K85: Gender 0 Female 1 Male | L85: Person.java | M85: =IF(OR(O85<>"", Q85<>""),"Yes","No") -> Yes | N85: sex_dv | O85: 02_create_ukhls_variables.do | P85: rb090 | Q85: 02_00_create_variables_**.do | S85: Demography | U85: Gender from sex_dv variable.
A86: dgnsp | C86: {=_xlfn.IFS(S86 = Modules!$A$2,Modules!$B$2,S86 = Modules!$A$3,Modules!$B$3,S86 = Modules!$A$4,Modules!$B$4,S86 = Modules!$A$5,Modules!$B$5,S86 = Modules!$A$6,Modules!$B$6,S86 = Modules!$A$7,Modules!$B$7,S86 = Modules!$A$8,Modules!$B$8,S86 = Modules!$A$9,Modules!$B$9,S86 = Modules!$A$10,Modules!$B$10,S86 = Modules!$A$11,Modules!$B$11,S86 = Modules!$A$12,Modules!$B$12, S86 = Modules!$A$13,Modules!$B$13)} -> dem | D86: Male | E86: Partner | H86: Flag | J86: =CONCATENATE(B86, C86,D86,E86,F86,G86,H86,I86) -> demMalePartnerFlag | K86: Gender 0 Female 1 Male | M86: =IF(OR(O86<>"", Q86<>""),"Yes","No") -> Yes | P86: dgn (rb090); idpartner (rb240; urtgrp) | Q86: 02_00_create_variables_**.do | S86: Demography
A87: dhe | C87: {=_xlfn.IFS(S87 = Modules!$A$2,Modules!$B$2,S87 = Modules!$A$3,Modules!$B$3,S87 = Modules!$A$4,Modules!$B$4,S87 = Modules!$A$5,Modules!$B$5,S87 = Modules!$A$6,Modules!$B$6,S87 = Modules!$A$7,Modules!$B$7,S87 = Modules!$A$8,Modules!$B$8,S87 = Modules!$A$9,Modules!$B$9,S87 = Modules!$A$10,Modules!$B$10,S87 = Modules!$A$11,Modules!$B$11,S87 = Modules!$A$12,Modules!$B$12, S87 = Modules!$A$13,Modules!$B$13)} -> health | G87: SelfRated | J87: =CONCATENATE(B87, C87,D87,E87,F87,G87,H87,I87) -> healthSelfRated | K87: Health status 1 Poor 2 Fair 3 Good 4 Very good 5 Excellent | L87: Person.java | M87: =IF(OR(O87<>"", Q87<>""),"Yes","No") -> Yes | N87: scsf1 | O87: 02_create_ukhls_variables.do | P87: ph010 | Q87: 02_00_create_variables_**.do | S87: Health | U87: Health_status from scsf1 variable. Reverse coded, so the higher the better (5 = Excellent, 4 = Very Good, 3 = Good, 2 = Fair, 1 = Poor). Wave 1 uses sf1 as SF-12 was not asked in the self-completion part.
A88: dhe_lag1 | C88: {=_xlfn.IFS(S88 = Modules!$A$2,Modules!$B$2,S88 = Modules!$A$3,Modules!$B$3,S88 = Modules!$A$4,Modules!$B$4,S88 = Modules!$A$5,Modules!$B$5,S88 = Modules!$A$6,Modules!$B$6,S88 = Modules!$A$7,Modules!$B$7,S88 = Modules!$A$8,Modules!$B$8,S88 = Modules!$A$9,Modules!$B$9,S88 = Modules!$A$10,Modules!$B$10,S88 = Modules!$A$11,Modules!$B$11,S88 = Modules!$A$12,Modules!$B$12, S88 = Modules!$A$13,Modules!$B$13)} -> health | G88: SelfRated | I88: L1 | J88: =CONCATENATE(B88, C88,D88,E88,F88,G88,H88,I88) -> healthSelfRatedL1 | K88: Lag(1) of dhe | L88: Person.java | M88: =IF(OR(O88<>"", Q88<>""),"Yes","No") -> No | S88: Health
A89: dhe_mcs | C89: {=_xlfn.IFS(S89 = Modules!$A$2,Modules!$B$2,S89 = Modules!$A$3,Modules!$B$3,S89 = Modules!$A$4,Modules!$B$4,S89 = Modules!$A$5,Modules!$B$5,S89 = Modules!$A$6,Modules!$B$6,S89 = Modules!$A$7,Modules!$B$7,S89 = Modules!$A$8,Modules!$B$8,S89 = Modules!$A$9,Modules!$B$9,S89 = Modules!$A$10,Modules!$B$10,S89 = Modules!$A$11,Modules!$B$11,S89 = Modules!$A$12,Modules!$B$12, S89 = Modules!$A$13,Modules!$B$13)} -> health | D89: Mental | F89: Mcs | J89: =CONCATENATE(B89, C89,D89,E89,F89,G89,H89,I89) -> healthMentalMcs | K89: SF-12 Mental Component Summary (MCS). Continuous scale with a range of 0 (low functioning) to 100 (high functioning) | L89: Person.java | M89: =IF(OR(O89<>"", Q89<>""),"Yes","No") -> Yes | N89: sf12mcs_dv | O89: 02_create_ukhls_variables.do | S89: Health
A90: dhe_mcs_lag1 | C90: {=_xlfn.IFS(S90 = Modules!$A$2,Modules!$B$2,S90 = Modules!$A$3,Modules!$B$3,S90 = Modules!$A$4,Modules!$B$4,S90 = Modules!$A$5,Modules!$B$5,S90 = Modules!$A$6,Modules!$B$6,S90 = Modules!$A$7,Modules!$B$7,S90 = Modules!$A$8,Modules!$B$8,S90 = Modules!$A$9,Modules!$B$9,S90 = Modules!$A$10,Modules!$B$10,S90 = Modules!$A$11,Modules!$B$11,S90 = Modules!$A$12,Modules!$B$12, S90 = Modules!$A$13,Modules!$B$13)} -> health | D90: Mental | F90: Mcs | I90: L1 | J90: =CONCATENATE(B90, C90,D90,E90,F90,G90,H90,I90) -> healthMentalMcsL1 | K90: Lag(1) of dhe_mcs | L90: Person.java | M90: =IF(OR(O90<>"", Q90<>""),"Yes","No") -> No | S90: Health
A91: dhe_mcs_mean | C91: {=_xlfn.IFS(S91 = Modules!$A$2,Modules!$B$2,S91 = Modules!$A$3,Modules!$B$3,S91 = Modules!$A$4,Modules!$B$4,S91 = Modules!$A$5,Modules!$B$5,S91 = Modules!$A$6,Modules!$B$6,S91 = Modules!$A$7,Modules!$B$7,S91 = Modules!$A$8,Modules!$B$8,S91 = Modules!$A$9,Modules!$B$9,S91 = Modules!$A$10,Modules!$B$10,S91 = Modules!$A$11,Modules!$B$11,S91 = Modules!$A$12,Modules!$B$12, S91 = Modules!$A$13,Modules!$B$13)} -> health | D91: Mental | F91: Mcs | H91: Avg | J91: =CONCATENATE(B91, C91,D91,E91,F91,G91,H91,I91) -> healthMentalMcsAvg | K91: Mean of dhe_mcs (gender-year; total-year) | L91: HealthStatistics.java | M91: =IF(OR(O91<>"", Q91<>""),"Yes","No") -> No | R91: File: HealthStatistics1.csv | S91: Health
A92: dhe_mcs_median | C92: {=_xlfn.IFS(S92 = Modules!$A$2,Modules!$B$2,S92 = Modules!$A$3,Modules!$B$3,S92 = Modules!$A$4,Modules!$B$4,S92 = Modules!$A$5,Modules!$B$5,S92 = Modules!$A$6,Modules!$B$6,S92 = Modules!$A$7,Modules!$B$7,S92 = Modules!$A$8,Modules!$B$8,S92 = Modules!$A$9,Modules!$B$9,S92 = Modules!$A$10,Modules!$B$10,S92 = Modules!$A$11,Modules!$B$11,S92 = Modules!$A$12,Modules!$B$12, S92 = Modules!$A$13,Modules!$B$13)} -> health | D92: Mental | F92: Mcs | H92: P50 | J92: =CONCATENATE(B92, C92,D92,E92,F92,G92,H92,I92) -> healthMentalMcsP50 | K92: Median of dhe_mcs (gender-year; total-year) | L92: HealthStatistics.java | M92: =IF(OR(O92<>"", Q92<>""),"Yes","No") -> No | R92: File: HealthStatistics1.csv | S92: Health
A93: dhe_mcs_p_10 | C93: {=_xlfn.IFS(S93 = Modules!$A$2,Modules!$B$2,S93 = Modules!$A$3,Modules!$B$3,S93 = Modules!$A$4,Modules!$B$4,S93 = Modules!$A$5,Modules!$B$5,S93 = Modules!$A$6,Modules!$B$6,S93 = Modules!$A$7,Modules!$B$7,S93 = Modules!$A$8,Modules!$B$8,S93 = Modules!$A$9,Modules!$B$9,S93 = Modules!$A$10,Modules!$B$10,S93 = Modules!$A$11,Modules!$B$11,S93 = Modules!$A$12,Modules!$B$12, S93 = Modules!$A$13,Modules!$B$13)} -> health | D93: Mental | F93: Mcs | H93: P10 | J93: =CONCATENATE(B93, C93,D93,E93,F93,G93,H93,I93) -> healthMentalMcsP10 | K93: Percentile (10) of dhe_mcs (gender-year; total-year) | L93: HealthStatistics.java | M93: =IF(OR(O93<>"", Q93<>""),"Yes","No") -> No | R93: File: HealthStatistics1.csv | S93: Health
A94: dhe_mcs_p_25 | C94: {=_xlfn.IFS(S94 = Modules!$A$2,Modules!$B$2,S94 = Modules!$A$3,Modules!$B$3,S94 = Modules!$A$4,Modules!$B$4,S94 = Modules!$A$5,Modules!$B$5,S94 = Modules!$A$6,Modules!$B$6,S94 = Modules!$A$7,Modules!$B$7,S94 = Modules!$A$8,Modules!$B$8,S94 = Modules!$A$9,Modules!$B$9,S94 = Modules!$A$10,Modules!$B$10,S94 = Modules!$A$11,Modules!$B$11,S94 = Modules!$A$12,Modules!$B$12, S94 = Modules!$A$13,Modules!$B$13)} -> health | D94: Mental | F94: Mcs | H94: P25 | J94: =CONCATENATE(B94, C94,D94,E94,F94,G94,H94,I94) -> healthMentalMcsP25 | K94: Percentile (25) of dhe_mcs (gender-year; total-year) | L94: HealthStatistics.java | M94: =IF(OR(O94<>"", Q94<>""),"Yes","No") -> No | R94: File: HealthStatistics1.csv | S94: Health
A95: dhe_mcs_p_75 | C95: {=_xlfn.IFS(S95 = Modules!$A$2,Modules!$B$2,S95 = Modules!$A$3,Modules!$B$3,S95 = Modules!$A$4,Modules!$B$4,S95 = Modules!$A$5,Modules!$B$5,S95 = Modules!$A$6,Modules!$B$6,S95 = Modules!$A$7,Modules!$B$7,S95 = Modules!$A$8,Modules!$B$8,S95 = Modules!$A$9,Modules!$B$9,S95 = Modules!$A$10,Modules!$B$10,S95 = Modules!$A$11,Modules!$B$11,S95 = Modules!$A$12,Modules!$B$12, S95 = Modules!$A$13,Modules!$B$13)} -> health | D95: Mental | F95: Mcs | H95: P75 | J95: =CONCATENATE(B95, C95,D95,E95,F95,G95,H95,I95) -> healthMentalMcsP75 | K95: Percentile (75) of dhe_mcs (gender-year; total-year) | L95: HealthStatistics.java | M95: =IF(OR(O95<>"", Q95<>""),"Yes","No") -> No | R95: File: HealthStatistics1.csv | S95: Health
A96: dhe_mcs_p_90 | C96: {=_xlfn.IFS(S96 = Modules!$A$2,Modules!$B$2,S96 = Modules!$A$3,Modules!$B$3,S96 = Modules!$A$4,Modules!$B$4,S96 = Modules!$A$5,Modules!$B$5,S96 = Modules!$A$6,Modules!$B$6,S96 = Modules!$A$7,Modules!$B$7,S96 = Modules!$A$8,Modules!$B$8,S96 = Modules!$A$9,Modules!$B$9,S96 = Modules!$A$10,Modules!$B$10,S96 = Modules!$A$11,Modules!$B$11,S96 = Modules!$A$12,Modules!$B$12, S96 = Modules!$A$13,Modules!$B$13)} -> health | D96: Mental | F96: Mcs | H96: P90 | J96: =CONCATENATE(B96, C96,D96,E96,F96,G96,H96,I96) -> healthMentalMcsP90 | K96: Percentile (100) of dhe_mcs (gender-year; total-year) | L96: HealthStatistics.java | M96: =IF(OR(O96<>"", Q96<>""),"Yes","No") -> No | R96: File: HealthStatistics1.csv | S96: Health
A97: dhe_mcssp | C97: {=_xlfn.IFS(S97 = Modules!$A$2,Modules!$B$2,S97 = Modules!$A$3,Modules!$B$3,S97 = Modules!$A$4,Modules!$B$4,S97 = Modules!$A$5,Modules!$B$5,S97 = Modules!$A$6,Modules!$B$6,S97 = Modules!$A$7,Modules!$B$7,S97 = Modules!$A$8,Modules!$B$8,S97 = Modules!$A$9,Modules!$B$9,S97 = Modules!$A$10,Modules!$B$10,S97 = Modules!$A$11,Modules!$B$11,S97 = Modules!$A$12,Modules!$B$12, S97 = Modules!$A$13,Modules!$B$13)} -> health | D97: Mental | E97: Partner | F97: Mcs | J97: =CONCATENATE(B97, C97,D97,E97,F97,G97,H97,I97) -> healthMentalPartnerMcs | K97: Partner's Self-rated health health - mental component | L97: Person.java | M97: =IF(OR(O97<>"", Q97<>""),"Yes","No") -> Yes | O97: 02_create_ukhls_variables.do | S97: Health
A98: dhe_pcs | C98: {=_xlfn.IFS(S98 = Modules!$A$2,Modules!$B$2,S98 = Modules!$A$3,Modules!$B$3,S98 = Modules!$A$4,Modules!$B$4,S98 = Modules!$A$5,Modules!$B$5,S98 = Modules!$A$6,Modules!$B$6,S98 = Modules!$A$7,Modules!$B$7,S98 = Modules!$A$8,Modules!$B$8,S98 = Modules!$A$9,Modules!$B$9,S98 = Modules!$A$10,Modules!$B$10,S98 = Modules!$A$11,Modules!$B$11,S98 = Modules!$A$12,Modules!$B$12, S98 = Modules!$A$13,Modules!$B$13)} -> health | D98: Physical | F98: Pcs | J98: =CONCATENATE(B98, C98,D98,E98,F98,G98,H98,I98) -> healthPhysicalPcs | K98: SF-12 Physical Component Summary (PCS). Continuous scale with a range of 0 (low functioning) to 100 (high functioning) | L98: Person.java | M98: =IF(OR(O98<>"", Q98<>""),"Yes","No") -> Yes | N98: sf12pcs_dv | O98: 02_create_ukhls_variables.do | S98: Health
A99: dhe_pcs_lag1 | C99: {=_xlfn.IFS(S99 = Modules!$A$2,Modules!$B$2,S99 = Modules!$A$3,Modules!$B$3,S99 = Modules!$A$4,Modules!$B$4,S99 = Modules!$A$5,Modules!$B$5,S99 = Modules!$A$6,Modules!$B$6,S99 = Modules!$A$7,Modules!$B$7,S99 = Modules!$A$8,Modules!$B$8,S99 = Modules!$A$9,Modules!$B$9,S99 = Modules!$A$10,Modules!$B$10,S99 = Modules!$A$11,Modules!$B$11,S99 = Modules!$A$12,Modules!$B$12, S99 = Modules!$A$13,Modules!$B$13)} -> health | D99: Physical | F99: Pcs | I99: L1 | J99: =CONCATENATE(B99, C99,D99,E99,F99,G99,H99,I99) -> healthPhysicalPcsL1 | K99: Lag(1) of dhe_pcs | L99: Person.java | M99: =IF(OR(O99<>"", Q99<>""),"Yes","No") -> No | S99: Health
A100: dhe_pcs_mean | C100: {=_xlfn.IFS(S100 = Modules!$A$2,Modules!$B$2,S100 = Modules!$A$3,Modules!$B$3,S100 = Modules!$A$4,Modules!$B$4,S100 = Modules!$A$5,Modules!$B$5,S100 = Modules!$A$6,Modules!$B$6,S100 = Modules!$A$7,Modules!$B$7,S100 = Modules!$A$8,Modules!$B$8,S100 = Modules!$A$9,Modules!$B$9,S100 = Modules!$A$10,Modules!$B$10,S100 = Modules!$A$11,Modules!$B$11,S100 = Modules!$A$12,Modules!$B$12, S100 = Modules!$A$13,Modules!$B$13)} -> health | D100: Physical | F100: Pcs | H100: Avg | J100: =CONCATENATE(B100, C100,D100,E100,F100,G100,H100,I100) -> healthPhysicalPcsAvg | K100: Mean of dhe_pcs (gender-year; total-year) | L100: HealthStatistics.java | M100: =IF(OR(O100<>"", Q100<>""),"Yes","No") -> No | R100: File: HealthStatistics1.csv | S100: Health
...

Sheet Rules
A1: 0. Local/temporary variables: i_
A2: 1. Module name. Example: Income (y)
A3: 2. Main attribute (if necessary). Example: Employment income (Emp)
A4: 3. Level (if applicable). Example: Household (hh)
A5: 4. Measurement (if applicable). Example: Gross/net/equivalised
A6: 5. Other information
A7: 6. Statistics type (if applicable). Example: Median/mean
B8: Number | C8: n
B9: Flag | C9: flag
B10: Mean | C10: avg
B11: Median | C11: p50
B12: Pctiles | C12: p##
B13: Categories | C13: c#
B14: Squared | C14: sq
B15: Share | C15: share
B16: Ratio | C16: ratio
A17: 7. Periodicity (if applicable). Example: Yearly/monthly
B18: Lag# | C18: l#

Sheet Modules
A1: Modules | B1: Acronym
A2: Demography | B2: dem
A3: Education | B3: edu
A4: Health | B4: health
A5: Social care | B5: care
A6: Labour | B6: lab
A7: Income | B7: y
A8: Consumption | B8: x
A9: Statistical display | B9: stat
A10: Covid | B10: covid
A11: Wealth | B11: wealth
A12: ID | B12: id
A13: Weight | B13: wgt

Sheet Abbreviations
A1: Word | B1: Abbreviation
A2: Activity | B2: ---
A3: Adjustment | B3: adj
A4: Age | B4: age
A5: Alignment | B5: align
A6: Benefit | B6: ben
A7: Benefit unit | B7: bu
A8: Children | B8: child
A9: Cohabiting | B9: --> partnership
A10: Composition | B10: comp
A11: Couple | B11: couple
A12: Cross-sectional | B12: cross
... A79: Yearly | B79: yrly

Sheet Coding Style
A1: Style | B1: Applicable to
A2: camelCase | B2: global, updated variables
A3: PascalCase | B3: Java Classes
A4: snake_case | B4: local, temporary variables | D4: start with i_

Sheet Country Specific Vars
A1: Country Specific Variables
A2: drgn / demRegion
B3: UK | C3: Region : NUTS Level 1 1 "North East" 2 "North West" 4 "Yorkshire and the Humber 5 "East Midlands" 6 "West Midlands" 7 "East of England" 8 "London" 9 "South East" 10 "South West" 11 "Wales" 12 "Scotland" 13 "Northern Ireland"
B4: PL | C4: Region: NUTS 1 2 "Poludniowy" 4 "Polnocno-Zachodni" 5 "Poludniowo-Zachodni" 6 "Polnocy" 10 "Central and East"
B5: IT | C5: Region: NUTS 1 3 "Northwest" 6 "South" 7 "Islands" 8 "Northeast" 9 "Central"
B6: HU | C6: Region: NUTS1 1 "Central Hungary" 2 "Transdanubia" 3 "Great Plain and North "
B7: EL | C7: Region: NUTS1 3 "Attica" 4 "Aegean Islands" 7 "Central and Northern Greece"
